Workbook
Name BDM_Name: Lookup!$U$2:$U$17
Name Billing_Month: Table3[Billing Month]
Name Billing_Month: Table3[Billing Month]
Name Billing_Status: Table4[Billing Status]
Name Billing_Status: Table4[Billing Status]
Name Deal_Probability: Table6[Deal Probability]
Name Deal_Probability: Table6[Deal Probability]
Name Deal_Status: Table2[Deal Status]
Name Deal_Status: Table2[Deal Status]
Name Deal_Type: Table7[Deal Type]
Name Deal_Type: Table7[Deal Type]
Name LOB_INPUT: Table1[LOB INPUT]
Name LOB_INPUT: Table1[LOB INPUT]
Name Sales_Vertical: Table8[Sales Vertical]
Name Sales_Vertical: Table8[Sales Vertical]
Name Source: Table5[Source]
Name Source: Table5[Source]

Sheet Lookup
A1: LOB INPUT | C1: Deal Status | E1: Billing Month | G1: Billing Status | I1: Source | K1: Deal Probability | M1: Deal Type | O1: Sales Vertical | U1: BDM Name
A2: ITSS Cisco LoB | C2: Commit | E2: 46113 | F2: FY 27 Q1 | G2: Yes | I2: Backlog Deal | K2: High | M2: Product | O2: Mining Indust&Health | Q2: Focus Needed | S2: New Engagement | U2: David Ramorola
A3: ITSS Dell Technologies LoB | C3: Upside | E3: 46143 | F3: FY 27 Q1 | G3: No | I3: Committed Pipe Deal | K3: Medium | M3: Software / Licence | O3: Corporate | Q3: Priority | S3: Pipeline | U3: Hein Botha
A4: ITSS Financing Solutions | E4: 46174 | F4: FY 27 Q1 | I4: Upside Deal | K4: Low | M4: OEM Service | O4: Public | Q4: Telkom R40m | U4: Johan Taljaard
A5: ITSS HPE LoB | E5: 46204 | F5: FY 27 Q2 | O5: FSI & Retail | Q5: Deals moved | U5: Lawrence Lethuba
A6: ITSS Huawei LoB | E6: 46235 | F6: FY 27 Q2 | O6: Other | Q6: Additional requirement | U6: Lebogang Ziqubu
A7: ITSS Oracle LoB | E7: 46266 | F7: FY 27 Q2 | O7: SAP Backlog / Invoiced | Q7: 1700 | U7: Mason Hlongwane
A8: ITSS Smart Office Connexion LoB | E8: 46296 | F8: FY 27 Q3 | Q8: R1700 upside | U8: Nowell Duze
A9: ITSS Tech Management | E9: 46327 | F9: FY 27 Q3 | Q9: R300m JB | U9: Ntokozo Maseko
A10: ITSS Technology Integration LoB | E10: 46357 | F10: FY 27 Q3 | U10: Olden Pieterse
A11: ITSS Workspace LoB | E11: 46388 | F11: FY 27 Q4 | U11: Paul van Rooyen
A12: Central BDM | E12: 46419 | F12: FY 27 Q4 | U12: Roan van Nieuwenhuizen
E13: 46447 | F13: FY 27 Q4 | U13: Sean Royds
E14: 46478 | F14: FY 28 Q1 | U14: Wandile Dlamini
E15: 46508 | F15: FY 28 Q1 | U15: Wes Beck
E16: 46539 | F16: FY 28 Q1 | U16: Wimpie Pieterse

Sheet Current Cadence
A1: LOB INPUT
D2: Totals | E2: =SUM(E4:E497) -> 9.9886404e+08 | F2: =SUM(F4:F161985) -> 7.5046369e+08 | G2: =SUM(G4:G161985) -> 77605851
A3: LOB INPUT | B3: Customer Name | C3: Sales Vertical | D3: OPP Number | E3: Gross Revenue | F3: Expected Net Revenue | G3: GP Value | H3: GP % | I3: Deal Status | J3: Billing Month | K3: FY Qrt list | L3: Billing Status | M3: Source | N3: Deal Probability | O3: Extra Notes | P3: Presales Name | Q3: LOB / BDM Name | R3: Deal Type | S3: Update | T3: Medium high chase
A4: ITSS Cisco LoB | B4: South African Revenue Services | C4: Public | D4: OPP145398 | E4: 2.4910934e+08 | F4: 2.4910934e+08 | G4: 19928747 | H4: 0.08 | I4: Upside | J4: 46447 | K4: FY 27 Q4 | L4: No | M4: Upside Deal | N4: Low | P4: David Ramorola | Q4: Wimpie Pieterse | R4: Product | S4: RFP - TowerD Secure Access, 1000Eyes, Meraki switches(5years)
A5: ITSS Cisco LoB | B5: South African Social Agency (SASSA) | C5: Public | D5: OPP146677 | E5: 1.235666e+08 | F5: 1.235666e+08 | G5: 6178330.2 | H5: 0.05 | I5: Upside | J5: 46447 | K5: FY 27 Q4 | L5: No | M5: Upside Deal | N5: Low | P5: David Ramorola | Q5: Wimpie Pieterse | R5: Product | S5: RFQ - Meraki SD-Wan + Security (Switches and Sec-SUITE)
A6: ITSS Cisco LoB | B6: The Spar Group Ltd | C6: FSI & Retail | D6: OPP136919 | E6: 38123456 | F6: 4574814.7 | G6: 4574814.7 | H6: 0.12 | I6: Upside | J6: 46174 | K6: FY 27 Q1 | L6: No | M6: Upside Deal | N6: High | O6: checked | P6: Roan van Nieuwenhuizen | Q6: Wimpie Pieterse | R6: Software / Licence | S6: Need to move Licenses to another ORG to reduce the License limit. This is before we can create Cisco Meraki EA
A7: ITSS Cisco LoB | B7: Telkom Consumer | C7: Mining Indust&Health | D7: OPP133098 | E7: 33825197 | F7: 1691259.9 | G7: 1691259.9 | H7: 0.05 | I7: Commit | J7: 46174 | K7: FY 27 Q1 | L7: No | M7: Backlog Deal | N7: High | O7: checked | P7: johan Taljaard | Q7: Wimpie Pieterse | R7: OEM Service | S7: SFC Annual Payment
A8: ITSS Cisco LoB | B8: Discovery Central Services (Pty) Ltd | C8: FSI & Retail | D8: OPP147096 | E8: 30614619 | F8: 30614619 | G8: 1530730.9 | H8: 0.05 | I8: Upside | J8: 46235 | K8: FY 27 Q2 | L8: No | M8: Upside Deal | N8: Low | O8: checked | P8: Paul van Rooyen | Q8: Wimpie Pieterse | R8: Product | S8: RFQ - Network refresh
A9: ITSS Cisco LoB | B9: Telkom ISP | C9: Mining Indust&Health | D9: OPP147364 | E9: 28723558 | F9: 2872355.8 | G9: 2872355.8 | H9: 0.1 | I9: Upside | J9: 46327 | K9: FY 27 Q3 | L9: No | M9: Upside Deal | N9: Medium | O9: checked | P9: Johan Taljaard | Q9: Wimpie Pieterse | R9: Software / Licence | S9: DDOS
A10: ITSS Cisco LoB | B10: Openserve | C10: Mining Indust&Health | D10: OPP145768 | E10: 21938053 | F10: 1096902.6 | G10: 1096902.6 | H10: 0.05 | I10: Upside | J10: 46327 | K10: FY 27 Q3 | L10: No | M10: Upside Deal | N10: Medium | O10: checked | P10: Johan Taljaard | Q10: Wimpie Pieterse | R10: Product | S10: FW budget prep 10 x FW's + secure workload
A11: ITSS Cisco LoB | B11: Telkom Consumer | C11: Mining Indust&Health | D11: OPP147259 | E11: 21938052 | F11: 21938052 | G11: 2193805.2 | H11: 0.1 | I11: Upside | J11: 46327 | K11: FY 27 Q3 | L11: No | M11: Upside Deal | N11: Low | O11: checked | P11: Johan Taljaard | Q11: Wimpie Pieterse | R11: Product | S11: Telkom BCX ACI FW Replace 67 Contexts
A12: ITSS Cisco LoB | B12: The Standard Bank of South Africa | C12: FSI & Retail | D12: OPP13777 | E12: 17211644 | F12: 1721164.4 | G12: 1721164.4 | H12: 0.1 | I12: Commit | J12: 46478 | L12: No | M12: Backlog Deal | N12: High | O12: Checked | P12: Paul van Rooyen | Q12: Wimpie Pieterse | R12: Software / Licence | S12: APP-D EA Renewal
A13: ITSS Cisco LoB | B13: Telkom Consumer | C13: Mining Indust&Health | D13: OPP135119/01 | E13: 15799289 | F13: 15799289 | G13: 1421936 | H13: 0.09 | I13: Upside | J13: 46327 | K13: FY 27 Q3 | L13: No | M13: Upside Deal | N13: Medium | O13: checked | P13: Johan Taljaard | Q13: Wimpie Pieterse | R13: Product | S13: EDD 154 days after order placement - Nutanix Expansion Value updated, Busy repricing will be resubmitted to Telkom
A14: ITSS Cisco LoB | B14: Openserve | C14: Mining Indust&Health | D14: OPP141512/01 | E14: 14895000 | F14: 14895000 | G14: 1489500 | H14: 0.1 | I14: Upside | J14: 46327 | K14: FY 27 Q3 | L14: No | M14: Upside Deal | N14: Medium | O14: checked | P14: Johan Taljaard | Q14: Wimpie Pieterse | R14: Product | S14: International POPS - Telkom wants eq for evaluation before project go ahead
A15: ITSS Cisco LoB | B15: SANBS | C15: Public | D15: OPP146783 | E15: 14433451 | F15: 721672.55 | G15: 721672.55 | H15: 0.05 | I15: Upside | J15: 46296 | K15: FY 27 Q3 | L15: No | M15: Upside Deal | N15: Low | O15: Checked | P15: Wandile Dlamini | Q15: Wimpie Pieterse | R15: OEM Service | S15: Current support expires at the end of Sep-2026
A16: ITSS Cisco LoB | B16: Nedbank Limited | C16: FSI & Retail | D16: OPP147252 | E16: 14378595 | F16: 862715.69 | G16: 862715.69 | H16: 0.06 | I16: Upside | J16: 46266 | K16: FY 27 Q2 | L16: No | M16: Upside Deal | N16: Low | P16: Sean Royds | Q16: Wimpie Pieterse | R16: Product | S16: Budgetsry for Jac-Lou Wireless Guest Portal Business Case
A17: ITSS Cisco LoB | B17: Openserve (Pty) Ltd | C17: Mining Indust&Health | D17: OPP145588 | E17: 13312345 | F17: 665617.25 | G17: 665617.25 | H17: 0.05 | I17: Upside | J17: 46174 | K17: FY 27 Q1 | L17: No | M17: Upside Deal | N17: High | O17: checked | P17: Johan Taljaard | Q17: Wimpie Pieterse | R17: OEM Service | S17: Opernserve Sweep Year 1 of 3
A18: ITSS Cisco LoB | B18: Woolworths (Pty) Limited | C18: FSI & Retail | D18: OPP128359 | E18: 13294957 | F18: 13294957 | G18: 1329495.7 | H18: 0.1 | I18: Commit | J18: 46266 | K18: FY 27 Q2 | L18: No | M18: Committed Pipe Deal | N18: High | P18: Olden Pieterse | Q18: Wimpie Pieterse | R18: Product | S18: Operate UC waiting for customer signature on contract
A19: ITSS Cisco LoB | B19: Telkom | C19: Mining Indust&Health | D19: OPP135119 | E19: 13162789 | F19: 13162789 | G19: 1316278.9 | H19: 0.1 | I19: Upside | J19: 46327 | K19: FY 27 Q3 | L19: No | M19: Upside Deal | N19: Medium | O19: checked | P19: Johan Taljaard | Q19: Wimpie Pieterse | R19: Product | S19: Telkom Nutanix expansion
A20: ITSS Cisco LoB | B20: Telkom Consumer | C20: Mining Indust&Health | D20: OPP142649/02 | E20: 13140597 | F20: 13140597 | G20: 1182653.7 | H20: 0.09 | I20: Upside | J20: 46327 | K20: FY 27 Q3 | L20: No | M20: Upside Deal | N20: Medium | O20: checked | P20: Johan Taljaard | Q20: Wimpie Pieterse | R20: Product | S20: EDD 42 days after order placement - EoL Switches & line cards
A21: ITSS Cisco LoB | B21: Openserve | C21: Mining Indust&Health | D21: OPP148548 | E21: 12449770 | F21: 12449770 | G21: =F21*H21 -> 1244977 | H21: 0.1 | I21: Upside | J21: 46327 | K21: =IF(J21="","",_xlfn.XLOOKUP(J21,Lookup!E:E,Lookup!F:F)) -> FY 27 Q3 | L21: No | M21: Upside Deal | N21: Medium | O21: OPP148548 Openserve SPINE Switches - Tygerburg & Core | P21: Johan Taljaard | Q21: Wimpie Pieterse | R21: Product
A22: ITSS Cisco LoB | B22: Air Traffic and Navigation ServicesCompany Limited | C22: Public | D22: OPP123907 | E22: 12000000 | F22: 12000000 | G22: 375152 | H22: 0.1 | I22: Upside | J22: 46447 | K22: FY 27 Q4 | L22: No | M22: Upside Deal | N22: Low | O22: Checked | P22: Wandile Dlamini | Q22: Wimpie Pieterse | R22: Product | S22: Ongoing Tender - Waiting for award for more than a year
A23: ITSS Cisco LoB | B23: Telkom SA SOC Limited | C23: Mining Indust&Health | D23: OPP122332/04 | E23: 11391262 | F23: 569563.1 | G23: 569563.1 | H23: 0.05 | I23: Commit | J23: 46204 | K23: FY 27 Q2 | L23: No | M23: Backlog Deal | N23: High | O23: checked | P23: johan Taljaard | Q23: Wimpie Pieterse | R23: OEM Service | S23: APP-D EA Year 2/3
A24: ITSS Cisco LoB | B24: Western Cape Government Health | C24: Public | D24: OPP140607 | E24: 10854175 | F24: 10854175 | G24: 542708.75 | H24: 0.05 | I24: Upside | J24: 46296 | K24: FY 27 Q3 | L24: No | M24: Upside Deal | N24: Low | O24: Checked | P24: Wandile Dlamini | Q24: Wimpie Pieterse | R24: Product | S24: EDD 45 days - LAN refresh - customer asked for bid evaluation extension until 01-Aug-2026
A25: ITSS Cisco LoB | B25: Telkom Consumer | C25: Mining Indust&Health | D25: OPP142649/01 | E25: 10827243 | F25: 10827243 | G25: 974451.85 | H25: 0.09 | I25: Upside | J25: 46327 | K25: FY 27 Q3 | L25: No | M25: Upside Deal | N25: Medium | O25: checked | P25: Johan Taljaard | Q25: Wimpie Pieterse | R25: Product | S25: EDD 58 days after order placement - Line Cards
A26: ITSS Cisco LoB | B26: Tiger Brands | C26: FSI & Retail | D26: OPP138466 | E26: 10753040 | F26: 860243.23 | G26: 860243.23 | H26: 0.08 | I26: Upside | J26: 46204 | K26: FY 27 Q2 | L26: No | M26: Upside Deal | N26: Low | O26: Checked | P26: Nowell Duze | Q26: Wimpie Pieterse | R26: Product | S26: Quote refreshed on the 18th of May. Vblock DC switches
A27: ITSS Cisco LoB | B27: Pep A Division Of Pepkor Trading (PTd | C27: Corporate | D27: OPP146179 | E27: 8123456 | F27: 974814.72 | G27: 974814.72 | H27: 0.12 | I27: Upside | J27: 46327 | K27: FY 27 Q3 | L27: No | M27: Upside Deal | N27: High | O27: checked | P27: Roan van Nieuwenhuizen | Q27: Wimpie Pieterse | R27: Software / Licence | S27: Working on a 3 and 5 year EA Renewal. Customer will release an RFQ, EA expiring in Nov 2026
A28: ITSS Cisco LoB | B28: Durban ICC | C28: Public | D28: OPP145736 | E28: 7845333 | F28: 7845333 | G28: 392266.65 | H28: 0.05 | I28: Upside | J28: 46266 | K28: FY 27 Q2 | L28: No | M28: Upside Deal | N28: Medium | O28: Checked | P28: Wandile Dlamini | Q28: Wimpie Pieterse | R28: Product | S28: EDD 100 days - Wireless refresh
A29: ITSS Cisco LoB | B29: Volkswagen Group Africa (Pty) Ltd | C29: Corporate | D29: OPP148038 | E29: 7461453 | F29: 7461453 | G29: 746145.3 | H29: 0.1 | I29: Upside | J29: 46235 | K29: FY 27 Q2 | L29: No | M29: Upside Deal | N29: Low | P29: Roan van Nieuwenhuizen | Q29: Wimpie Pieterse | R29: Product | S29: Respond to RFQ for Kariga Firewals
A30: ITSS Cisco LoB | B30: Electoral Commission of SouthAfrica Iec | C30: Public | D30: OPP147418 | E30: 7405205 | F30: 7405205 | G30: 740520.5 | H30: 0.1 | I30: Upside | J30: 46266 | K30: FY 27 Q2 | L30: No | M30: Upside Deal | N30: Low | P30: Roan van Nieuwenhuizen | Q30: Wimpie Pieterse | R30: Product | S30: IEC Wireless Solution
A31: ITSS Cisco LoB | B31: Electoral Commission of SouthAfrica Iec | C31: Public | D31: OPP139758 | E31: 7056976.2 | F31: 1372145.7 | G31: 705697.62 | H31: 0.1 | I31: Commit | J31: 46235 | K31: FY 27 Q2 | L31: No | M31: Backlog Deal | N31: High | O31: Checked | P31: David Ramorola | Q31: Wimpie Pieterse | R31: Software / Licence | S31: Contract start date 1 August
A32: ITSS Cisco LoB | B32: Pep A Division Of Pepkor Trading (PTd | C32: Corporate | D32: OPP141566 | E32: 6991803.2 | F32: 6991803.2 | G32: 489426.23 | H32: 0.07 | I32: Upside | J32: 46419 | K32: FY 27 Q4 | L32: No | M32: Upside Deal | N32: Medium | O32: checked | P32: Paul van Rooyen | Q32: Wimpie Pieterse | R32: Product | S32: Capfin Catalyst refresh
A33: ITSS Cisco LoB | B33: Nedbank Limited | C33: FSI & Retail | D33: OPP147043 | E33: 5790700.2 | F33: 5790700.2 | G33: 347442.01 | H33: 0.06 | I33: Commit | J33: 46204 | K33: FY 27 Q2 | L33: No | M33: Backlog Deal | N33: High | P33: Sean Royds | Q33: Wimpie Pieterse | R33: Product | S33: EDD 16 July; Shuaib will push to add to NBV Jul signoff
A34: ITSS Cisco LoB | B34: Volkswagen Group Africa (Pty) Ltd | C34: Corporate | D34: OPP146486 | E34: 5751314 | F34: 5751314 | G34: 575131.4 | H34: 0.1 | I34: Upside | J34: 46235 | K34: FY 27 Q2 | L34: No | M34: Upside Deal | N34: Low | P34: Roan van Nieuwenhuizen | Q34: Wimpie Pieterse | R34: Product | S34: Provide Security EA Proposal
A35: ITSS Cisco LoB | B35: Capitec Bank Limited | C35: FSI & Retail | D35: OPP089485 | E35: 5699203 | F35: 159577.68 | G35: 159577.68 | H35: 0.028 | I35: Commit | J35: 46327 | K35: FY 27 Q3 | L35: No | M35: Backlog Deal | N35: High | O35: checked | P35: Paul van Rooyen | Q35: Wimpie Pieterse | R35: Software / Licence | S35: SDWAN EA Annual payment
A36: ITSS Cisco LoB | B36: Tiger Brands | C36: FSI & Retail | D36: OPP146660 | E36: 5301769.3 | F36: 5301769.3 | G36: 424141.55 | H36: 0.08 | I36: Upside | J36: 46204 | K36: FY 27 Q2 | L36: No | M36: Upside Deal | N36: Low | O36: Checked | P36: Nowell Duze | Q36: Wimpie Pieterse | R36: Product | S36: Bafo Pricing submitted on the 22nd May 2026
A37: ITSS Cisco LoB | B37: Momentum Metropolitan Life Ltd Metropolitan | C37: FSI & Retail | D37: OPP142558 | E37: 5238762.6 | F37: 5238762.6 | G37: 628651.51 | H37: 0.12 | I37: Commit | J37: 46143 | K37: FY 27 Q1 | L37: Yes | M37: Backlog Deal | N37: High | O37: Checked | P37: Wandile Dlamini | Q37: Wimpie Pieterse | R37: Product | S37: EDD 196 days after order placement - New Rivonia branch
A38: ITSS Cisco LoB | B38: PepsiCo South Africa (Pty) Ltd | C38: Corporate | D38: OPP144981 | E38: 4973229.5 | F38: 4973229.5 | G38: 248661 | H38: 0.045 | I38: Upside | J38: 46235 | K38: =IF(J38="","",_xlfn.XLOOKUP(J38,Lookup!E:E,Lookup!F:F)) -> FY 27 Q2 | L38: No | M38: Upside Deal | N38: Medium | P38: Olden Pieterse | Q38: Wimpie Pieterse | R38: Product | S38: Submitted Quote : 28/5/2026
A39: ITSS Cisco LoB | B39: Sanlam Life Insurance Limited | C39: FSI & Retail | D39: OPP137867 | E39: 4963898 | F39: 4963898 | G39: 496389.8 | H39: 0.1 | I39: Upside | J39: 46235 | K39: FY 27 Q2 | L39: No | M39: Upside Deal | N39: Medium | P39: Sean Royds | Q39: Wimpie Pieterse | R39: Product | S39: EDD 56 days after order placement - Assupol SD-WAN Routers
A40: ITSS Cisco LoB | B40: Sanlam Life Insurance Limited | C40: FSI & Retail | D40: OPP145901 | E40: 4249038.3 | F40: 4249038.3 | G40: 424903.83 | H40: 0.1 | I40: Commit | J40: 46327 | K40: FY 27 Q3 | L40: No | M40: Backlog Deal | N40: High | P40: Sean Royds | Q40: Wimpie Pieterse | R40: Product | S40: EDD 3 June 2026
A41: ITSS Cisco LoB | B41: AVI Financial Services (Pty) Ltd | C41: Corporate | D41: OPP125425/13 | E41: 4181579.7 | F41: 209078.99 | G41: 209078.99 | H41: 0.05 | I41: Upside | J41: 46296 | K41: FY 27 Q3 | L41: No | M41: Upside Deal | N41: High | O41: checked | P41: Lawrence Lethuba | Q41: Wimpie Pieterse | R41: Software / Licence | S41: OPP125425_13 - AVI - EA - 60 Months & 84 Months_V5
A42: ITSS Cisco LoB | B42: Sasol South Africa Limited | C42: Mining Indust&Health | D42: OPP147303 | E42: 4120766.5 | F42: 4120766.5 | G42: 412076.65 | H42: 0.1 | I42: Commit | J42: 46174 | K42: FY 27 Q1 | L42: No | M42: Backlog Deal | N42: High | O42: Checked | P42: Nowell Duze | Q42: Wimpie Pieterse | R42: Product | S42: Project missing Persons( Industrial switches) shipdate 5th August Duplicate please remove
A43: ITSS Cisco LoB | B43: Sanlam Life Insurance Limited | C43: FSI & Retail | D43: OPP145900 | E43: 4059485.9 | F43: 4059485.9 | G43: 405948.59 | H43: 0.1 | I43: Commit | J43: 46235 | K43: FY 27 Q2 | L43: No | M43: Backlog Deal | N43: High | P43: Sean Royds | Q43: Wimpie Pieterse | R43: Product | S43: EDD 29 July 2026
A44: ITSS Cisco LoB | B44: Sasol South Africa Limited | C44: Mining Indust&Health | D44: OPP146361 | E44: 4057210.5 | F44: 4057210.5 | G44: 405721.05 | H44: 0.1 | I44: Commit | J44: 46204 | K44: FY 27 Q2 | L44: No | M44: Backlog Deal | N44: High | O44: Checked | P44: Nowell Duze | Q44: Wimpie Pieterse | R44: Product | S44: Project missing Persons( Industrial switches) shipdate 5th August
A45: ITSS Cisco LoB | B45: Sanlam Life Insurance Limited | C45: FSI & Retail | D45: OPP146115 | E45: 3926119.1 | F45: 3926119.1 | G45: 392611.91 | H45: 0.1 | I45: Upside | J45: 46235 | K45: FY 27 Q2 | L45: No | M45: Upside Deal | N45: Medium | P45: Sean Royds | Q45: Wimpie Pieterse | R45: Product | S45: Sanlam reviewing to potentially bundle deals together
A46: ITSS Cisco LoB | B46: Nedbank Limited | C46: FSI & Retail | D46: OPP146264 | E46: 3303945 | F46: =E46 -> 3303945 | G46: =F46*H46 -> 198236.7 | H46: 0.06 | I46: Commit | J46: 46143 | K46: FY 27 Q1 | L46: No | M46: Backlog Deal | N46: High | O46: Checked | P46: Sean Royds | Q46: Wimpie Pieterse | R46: Product | S46: Partial Invoice Chassis in May, Awaiting SFP's due Jun (EDD 29 May 2026)
A47: ITSS Cisco LoB | B47: Woolworths (Pty) Limited | C47: FSI & Retail | D47: OPP125614 | E47: 3549755 | F47: 3532442.3 | G47: 353244.23 | H47: 0.1 | I47: Commit | J47: 46174 | K47: FY 27 Q1 | L47: No | M47: Backlog Deal | N47: High | P47: Olden Pieterse | Q47: Wimpie Pieterse | R47: Product | S47: EDD 196 days from order - DC3 refresh
A48: ITSS Cisco LoB | B48: AVI Financial Services (Pty) Ltd | C48: Corporate | D48: OPP132983 | E48: 3498223.4 | F48: 3498223.4 | G48: 174911.17 | H48: 0.05 | I48: Upside | J48: 46266 | K48: FY 27 Q2 | L48: No | M48: Upside Deal | N48: High | O48: checked | P48: Lawrence Lethuba | Q48: Wimpie Pieterse | R48: Product | S48: EDD 58 days after order placement - EoL Replacements Bryanston HQ - Awaiting customer decision - awaiting Andre
A49: ITSS Cisco LoB | B49: AVI Financial Services (Pty) Ltd | C49: Corporate | D49: OPP125425/14 | E49: 3341660.3 | F49: 3341660.3 | G49: 167083.02 | H49: 0.05 | I49: Upside | J49: 46266 | K49: FY 27 Q2 | L49: No | M49: Upside Deal | N49: Medium | O49: checked | P49: Lawrence Lethuba | Q49: Wimpie Pieterse | R49: Product | S49: EDD 42 days after order placement - Network refresh for Isando DC
A50: ITSS Cisco LoB | B50: FNZ Software Solutions | C50: Corporate | D50: OPP146221 | E50: 3158297 | F50: 3158297 | G50: 315829.7 | H50: 0.1 | I50: Upside | J50: 46296 | K50: FY 27 Q3 | L50: No | M50: Upside Deal | N50: Medium | O50: Checked | P50: Wandile Dlamini | Q50: Wimpie Pieterse | R50: Product | S50: EDD 135 days for the SFPs
A51: ITSS Cisco LoB | B51: Sanlam Life Insurance Limited | C51: FSI & Retail | D51: OPP146954 | E51: 3127270.3 | F51: 312727.03 | G51: 312727.03 | H51: 0.1 | I51: Upside | J51: 46266 | K51: FY 27 Q2 | L51: No | M51: Upside Deal | N51: High | P51: Sean Royds | Q51: Wimpie Pieterse | R51: Product | S51: Sanlam reviewing to potentially bundle deals together
A52: ITSS Cisco LoB | B52: Run Rate | C52: SAP Backlog / Invoiced | D52: TBC | E52: 3115500.8 | F52: 3115500.8 | G52: 280395.08 | H52: 0.09 | I52: Upside | J52: 46174 | K52: FY 27 Q1 | L52: No | M52: Upside Deal | N52: High | Q52: Wimpie Pieterse | R52: Product
A53: ITSS Cisco LoB | B53: MR PRICE | C53: FSI & Retail | D53: OPP147804 | E53: 3083916.6 | F53: 308391.66 | G53: 308391.66 | H53: 0.1 | I53: Upside | J53: 46204 | K53: FY 27 Q2 | L53: No | M53: Upside Deal | N53: Low | P53: Olden Pieterse | Q53: Wimpie Pieterse | R53: Product | S53: Submitted pricing to Mr Price: Speculation at this point
A54: ITSS Cisco LoB | B54: AVI Financial Services (Pty) Ltd | C54: Corporate | D54: OPP125425/08 | E54: 3066160 | F54: 3066160 | G54: 153308 | H54: 0.05 | I54: Upside | J54: 46266 | K54: FY 27 Q2 | L54: No | M54: Upside Deal | N54: High | O54: checked | P54: Lawrence Lethuba | Q54: Wimpie Pieterse | R54: Product | S54: EDD 42 days after order placement - EoL Replacements Retail stores
A55: ITSS Cisco LoB | B55: Old Mutual Insure | C55: FSI & Retail | D55: OPP144877 | E55: 3000000 | F55: 300000 | G55: 300000 | H55: 0.1 | I55: Upside | J55: 46296 | K55: FY 27 Q3 | L55: No | M55: Upside Deal | N55: Medium | P55: Sean Royds | Q55: Wimpie Pieterse | R55: Product | S55: DC and Wireless Reresh towards latter part of CY 2026 or early CY 2027
A56: ITSS Cisco LoB | B56: Nedbank Limited | C56: FSI & Retail | D56: OPP146356 | E56: 2929292.9 | F56: 241318.76 | G56: 241318.76 | H56: 0.056 | I56: Upside | J56: 46419 | K56: FY 27 Q4 | L56: No | M56: Upside Deal | N56: High | P56: Sean Royds | Q56: Wimpie Pieterse | R56: Software / Licence | S56: Licensing Renewal, want to include this in the current EA as addition Tier, currnet licenses expire end May 2026
A57: ITSS Cisco LoB | B57: Ethekwini Municipality | C57: Public | D57: OPP146897 | E57: 2855832 | F57: 2855832 | G57: 142791.6 | H57: 0.05 | I57: Upside | J57: 46235 | K57: FY 27 Q2 | L57: No | M57: Upside Deal | N57: Low | O57: Checked | P57: Wandile Dlamini | Q57: Wimpie Pieterse | R57: Product | S57: EDD 105 - Network refresh - Wireless and MetroE routers
A58: ITSS Cisco LoB | B58: Investec Bank Limited | C58: FSI & Retail | D58: OPP139009 | E58: 2849544.4 | F58: 2849544.4 | G58: 341945.33 | H58: 0.12 | I58: Upside | J58: 46235 | K58: FY 27 Q2 | L58: No | M58: Upside Deal | N58: Low | P58: Sean Royds | Q58: Wimpie Pieterse | R58: Product | S58: EDD 42 days after order placement - ACI hardware replacement
A59: ITSS Cisco LoB | B59: Cape Peninsula University of Techno | C59: Public | D59: OPP146451 | E59: 2750816.6 | F59: 2304216.6 | G59: 275081.66 | H59: 0.1 | I59: Commit | J59: 46235 | K59: FY 27 Q2 | L59: No | M59: Backlog Deal | N59: High | P59: Olden Pieterse | Q59: Wimpie Pieterse | R59: Product | S59: EDD 16 July -
A60: ITSS Cisco LoB | B60: Mossel Bay Municipality | C60: Public | D60: OPP145648 | E60: 2725320 | F60: 2725320 | G60: 272532 | H60: 0.1 | I60: Upside | J60: 46266 | K60: FY 27 Q2 | L60: No | M60: Upside Deal | N60: Low | O60: Checked | P60: Wandile Dlamini | Q60: Wimpie Pieterse | R60: Product | S60: EDD 57 days - IP phones and Voice Gateway - Includes SIP services
A61: ITSS Cisco LoB | B61: Sanlam Life Insurance Limited | C61: FSI & Retail | D61: OPP146567 | E61: 2723042.2 | F61: 2723042.2 | G61: 272304.22 | H61: 0.1 | I61: Upside | J61: 46204 | K61: FY 27 Q2 | L61: No | M61: Upside Deal | N61: Medium | P61: Sean Royds | Q61: Wimpie Pieterse | R61: Product | S61: EDD 70 days from order placement - SGT 2027 EOL Replacements
A62: ITSS Cisco LoB | B62: RCL Consumer - Randfontein | C62: Corporate | D62: OPP146935 | E62: 2718159.6 | F62: 2718159.6 | G62: 271815.96 | H62: 0.1 | I62: Upside | J62: 46327 | K62: FY 27 Q3 | L62: No | M62: Upside Deal | N62: High | O62: Checked | P62: Hein Botha | Q62: Wimpie Pieterse | R62: Product | S62: EDD126 days for 9174AP :: OPP146994 Concentrix AA Bldg 11th Floor
A63: ITSS Cisco LoB | B63: Openserve (Pty) Ltd | C63: Mining Indust&Health | D63: OPP131296 | E63: 2708682 | F63: 270868.2 | G63: 270868.2 | H63: 0.1 | I63: Commit | J63: 46174 | K63: FY 27 Q1 | L63: No | M63: Backlog Deal | N63: High | O63: checked | P63: Johan Taljaard | Q63: Wimpie Pieterse | R63: OEM Service | S63: Cisco Advanced Services
A64: ITSS Cisco LoB | B64: Nelson Mandela Children's Hospital | C64: Public | D64: OPP148147 | E64: 2703682.7 | F64: 2703682.7 | G64: 324441.92 | H64: 0.12 | I64: Upside | J64: 46266 | K64: FY 27 Q2 | L64: No | M64: Upside Deal | N64: Low | O64: Checked | P64: Wandile Dlamini | Q64: Wimpie Pieterse | R64: Product | S64: EDD 120 days for the WLC - RFQ Wireless refresh
A65: ITSS Cisco LoB | B65: AVI Financial Services (Pty) Ltd | C65: Corporate | D65: OPP137317 | E65: 2701274.2 | F65: 2701274.2 | G65: 135063.71 | H65: 0.05 | I65: Upside | J65: 46266 | K65: FY 27 Q2 | L65: No | M65: Upside Deal | N65: High | O65: checked | P65: Lawrence Lethuba | Q65: Wimpie Pieterse | R65: Product | S65: EDD 44 days after order placement - EoL Replacements Isando Biscuits
A66: ITSS Cisco LoB | B66: The Spar Group Ltd | C66: FSI & Retail | D66: OPP147253 | E66: 2665953 | F66: 2665953 | G66: 319914.36 | H66: 0.12 | I66: Commit | J66: 46235 | K66: FY 27 Q2 | L66: No | M66: Backlog Deal | N66: High | P66: Olden Pieterse | Q66: Wimpie Pieterse | R66: Product | S66: EDD 18 June - VC equipment
A67: ITSS Cisco LoB | B67: South32 - Hillside Aluminium | C67: Mining Indust&Health | D67: OPP141257 | E67: 2586450.1 | F67: 2586450.1 | G67: 232780.51 | H67: 0.09 | I67: Upside | J67: 46327 | K67: FY 27 Q3 | L67: No | M67: Upside Deal | N67: Medium | O67: Checked | P67: Hein Botha | Q67: Wimpie Pieterse | R67: Product
A68: ITSS Cisco LoB | B68: TFG | C68: FSI & Retail | D68: OPP147999/01 | E68: 2567313.9 | F68: 128365.69 | G68: 128365.69 | H68: 0.05 | I68: Upside | J68: 46204 | K68: FY 27 Q2 | L68: No | M68: Upside Deal | N68: Low | P68: Olden Pieterse | Q68: Wimpie Pieterse | R68: Product | S68: Ndabeni Switches - Submitted Quote
A69: ITSS Cisco LoB | B69: South32 - Hotazel | C69: Mining Indust&Health | D69: OPP148302 | E69: 2499316.6 | F69: 2499316.6 | G69: 224938.5 | H69: 0.09 | I69: Upside | J69: 46235 | K69: FY 27 Q2 | L69: No | M69: Upside Deal | N69: High | P69: Hein Botha | Q69: Wimpie Pieterse | R69: Product | S69: Waiting for budget, should place the order end of June
A70: ITSS Cisco LoB | B70: Momentum Group-Wide Services (Pty) Ltd | C70: FSI & Retail | D70: OPP113848/04 | E70: 2326283 | F70: 232628.3 | G70: 232628.3 | H70: 0.1 | I70: Commit | J70: 46266 | K70: FY 27 Q2 | L70: No | M70: Backlog Deal | N70: High | O70: Checked | P70: Paul van Rooyen | Q70: Wimpie Pieterse | R70: Software / Licence | S70: Stanlib APP-D year 2/3
A71: ITSS Cisco LoB | B71: Telkom SA SOC Limited | C71: Mining Indust&Health | D71: OPP125388/06 | E71: 2227444.7 | F71: 2227141.6 | G71: 222714.16 | H71: 0.1 | I71: Commit | J71: 46174 | K71: FY 27 Q1 | L71: No | M71: Backlog Deal | N71: High | O71: checked | P71: Johan Taljaard | Q71: Wimpie Pieterse | R71: Product | S71: EDD Late May - Telkom TCnet Campus Refresh, business case is approved, contract still pending
A72: ITSS Cisco LoB | B72: TFG | C72: FSI & Retail | D72: OPP147999/03 | E72: 2130637.6 | F72: 106531.88 | G72: 106531.88 | H72: 0.05 | I72: Upside | J72: 46204 | K72: FY 27 Q2 | L72: No | M72: Upside Deal | N72: Low | P72: Olden Pieterse | Q72: Wimpie Pieterse | R72: Product | S72: Prestige Maitland Switches - - Submitted Quote
A73: ITSS Cisco LoB | B73: Woolworths (Pty) Limited | C73: FSI & Retail | D73: OPP101644 | E73: 2128385 | F73: 212838.5 | G73: 212838.5 | H73: 0.1 | I73: Commit | J73: 46296 | K73: FY 27 Q3 | L73: No | M73: Backlog Deal | N73: High | O73: Checked | P73: Olden Pieterse | Q73: Wimpie Pieterse | R73: Software / Licence | S73: Annual EA Renewal
A74: ITSS Cisco LoB | B74: Openserve | C74: Mining Indust&Health | D74: OPP148228 | E74: 2082663.5 | F74: 2082663.5 | G74: =F74*H74 -> 208266.35 | H74: 0.1 | I74: Upside | J74: 46296 | K74: =IF(J74="","",_xlfn.XLOOKUP(J74,Lookup!E:E,Lookup!F:F)) -> FY 27 Q3 | L74: No | M74: Upside Deal | N74: Medium | O74: OPP148228 - Openserve WAE Renewal | P74: Johan Taljaard | Q74: Wimpie Pieterse | R74: Software / Licence
A75: ITSS Cisco LoB | B75: Blake & Assosiates | C75: Corporate | D75: OPP146206 | E75: 2057983 | F75: 2057983 | G75: 205798.3 | H75: 0.1 | I75: Commit | J75: 46235 | K75: FY 27 Q2 | L75: No | M75: Backlog Deal | N75: High | O75: checked | P75: Johan Taljaard | Q75: Wimpie Pieterse | R75: Product | S75: Distribution, access switches and AP's
A76: ITSS Cisco LoB | B76: Bigen Africa Group Holdings | C76: Corporate | D76: OPP132134 | E76: 1945541.9 | F76: 1945541.9 | G76: 194554.19 | H76: 0.1 | I76: Commit | J76: 46174 | K76: FY 27 Q1 | L76: No | M76: Backlog Deal | N76: High | O76: Checked | P76: Wandile Dlamini | Q76: Wimpie Pieterse | R76: Product | S76: Delivered, waiting for invoice / Invoiced 90990473 (2026/03/24) but Installation by Field Services Outstanding
A77: ITSS Cisco LoB | B77: Umngeni Local Municipality | C77: Public | D77: OPP146253 | E77: 1891682 | F77: 1891682 | G77: 189168.2 | H77: 0.1 | I77: Upside | J77: 46296 | K77: FY 27 Q3 | L77: No | M77: Upside Deal | N77: Low | O77: Checked | P77: Wandile Dlamini | Q77: Wimpie Pieterse | R77: Product | S77: EDD 76 days - Network refresh - Includes connectivity and managed services
A78: ITSS Cisco LoB | B78: Nedbank Limited | C78: FSI & Retail | D78: OPP147618 | E78: 1819776 | F78: 109186.56 | G78: 109186.56 | H78: 0.06 | I78: Upside | J78: 46327 | K78: FY 27 Q3 | L78: No | M78: Upside Deal | N78: Low | P78: Sean Royds | Q78: Wimpie Pieterse | R78: Product | S78: Budgetsry for Jac-Lou Wireless Guest Portal Business Case - Additional AP's
A79: ITSS Cisco LoB | B79: Openserve | C79: Mining Indust&Health | D79: OPP141512 | E79: 1729924 | F79: 172992.4 | G79: 172992.4 | H79: 0.1 | I79: Upside | J79: 46447 | K79: FY 27 Q4 | L79: No | M79: Upside Deal | N79: Medium | O79: checked | P79: Johan Taljaard | Q79: Wimpie Pieterse | R79: OEM Service | S79: Cisco prof services for int pops
A80: ITSS Cisco LoB | B80: Citadel Financial Services | C80: Corporate | D80: OPP141437 | E80: 1688249.1 | F80: 1688249.1 | G80: 168824.91 | H80: 0.1 | I80: Commit | J80: 46235 | K80: FY 27 Q2 | L80: No | M80: Backlog Deal | N80: High | O80: checked | P80: Lawrence Lethuba | Q80: Wimpie Pieterse | R80: Product | S80: LAN Refresh
A81: ITSS Cisco LoB | B81: TFG | C81: FSI & Retail | D81: OPP147999/04 | E81: 1681132.8 | F81: 84056.639 | G81: 84056.639 | H81: 0.05 | I81: Upside | J81: 46204 | K81: FY 27 Q2 | L81: No | M81: Upside Deal | N81: Low | P81: Olden Pieterse | Q81: Wimpie Pieterse | R81: Product | S81: Prestige MaitlandWireless - - Submitted Quote
A82: ITSS Cisco LoB | B82: Tiger Brands | C82: FSI & Retail | D82: OPP146069 | E82: 1572349.9 | F82: 1572349.9 | G82: 125787.99 | H82: 0.08 | I82: Commit | J82: 46204 | K82: FY 27 Q2 | L82: No | M82: Backlog Deal | N82: High | O82: Checked | P82: Nowell Duze | Q82: Wimpie Pieterse | R82: Product | S82: Shipping date 11, 17 & 22 May 2026 + 2 Weeks to BCX Warehouse if no delays
A83: ITSS Cisco LoB | B83: Volkswagen Group Africa (Pty) Ltd | C83: Corporate | D83: OPP147266 | E83: 1355862 | F83: 1355862 | G83: 135586.2 | H83: 0.1 | I83: Upside | J83: 46235 | K83: FY 27 Q2 | L83: No | M83: Upside Deal | N83: Low | P83: Roan van Nieuwenhuizen | Q83: Wimpie Pieterse | R83: Product | S83: Respond to RFQ for Regional Firewalls
A84: ITSS Cisco LoB | B84: TFG | C84: FSI & Retail | D84: OPP147999/02 | E84: 1343561.1 | F84: 67178.056 | G84: 67178.056 | H84: 0.05 | I84: Upside | J84: 46204 | K84: FY 27 Q2 | L84: No | M84: Upside Deal | N84: Low | P84: Olden Pieterse | Q84: Wimpie Pieterse | R84: Product | S84: Ndabeni Wireless - Submitted Quote
A85: ITSS Cisco LoB | B85: Department of Home Affairs | C85: Public | D85: OPP144576 | E85: 1290725 | F85: 1290725 | G85: 129072.5 | H85: 0.1 | I85: Commit | J85: 46174 | K85: FY 27 Q1 | L85: No | M85: Backlog Deal | N85: High | P85: David Ramorola | Q85: Wimpie Pieterse | R85: Product | S85: Equipment is in our Warehouse
A86: ITSS Cisco LoB | B86: Sanlam Life Insurance Limited | C86: FSI & Retail | D86: OPP145570 | E86: 1289968.4 | F86: 1289968.4 | G86: 128996.84 | H86: 0.1 | I86: Commit | J86: 46174 | K86: FY 27 Q1 | L86: No | M86: Backlog Deal | N86: High | P86: Sean Royds | Q86: Wimpie Pieterse | R86: Product | S86: EDD 3 June 2026 - Additional Line Card modules
A87: ITSS Cisco LoB | B87: Total Energies | C87: Mining Indust&Health | D87: OPP138240 | E87: 1216303 | F87: 1216303 | G87: 121630.3 | H87: 0.1 | I87: Upside | J87: 46296 | K87: FY 27 Q3 | L87: No | M87: Upside Deal | N87: Low | P87: Mason Hlongwane | Q87: Wimpie Pieterse | R87: Product | S87: EDD 50 days after order placement - VC Unit, Waiting for update as is for New Site.
A88: ITSS Cisco LoB | B88: Sanlam Life Insurance Limited | C88: FSI & Retail | D88: OPP147796 | E88: 1209059.3 | F88: 1209059.3 | G88: 120905 | H88: 0.1 | I88: Upside | J88: 46235 | K88: =IF(J88="","",_xlfn.XLOOKUP(J88,Lookup!E:E,Lookup!F:F)) -> FY 27 Q2 | L88: No | M88: Upside Deal | N88: High | P88: Sean Royds | Q88: Wimpie Pieterse | R88: Product | S88: Shane will check progress with Umar.
A89: ITSS Cisco LoB | B89: Shoprite | C89: FSI & Retail | D89: OPP141634 | E89: 1161340 | F89: 1161340 | G89: 81293.799 | H89: 0.07 | I89: Upside | J89: 46235 | K89: FY 27 Q2 | L89: No | M89: Upside Deal | N89: Medium | P89: Olden Pieterse | Q89: Wandile Dlamini | R89: Product | S89: EDD 64 days from order - OPP145772 Concentrix Arch Bldg Durban
A90: ITSS Cisco LoB | B90: Pioneer Foods (Pty) Ltd | C90: FSI & Retail | D90: OPP131208/04 | E90: 1104339 | F90: 1104339 | G90: 110433.9 | H90: 0.1 | I90: Commit | J90: 46235 | K90: FY 27 Q1 | L90: No | M90: Backlog Deal | N90: High | P90: Olden Pieterse | Q90: Wimpie Pieterse | R90: Product | S90: EDD May - Aeroton Bakery - order received
A91: ITSS Cisco LoB | B91: Sanlam Life Insurance Limited | C91: FSI & Retail | D91: OPP146430 | E91: 1086871.8 | F91: 1086871.8 | G91: 108687.18 | H91: 0.06 | I91: Upside | J91: 46204 | K91: FY 27 Q2 | L91: No | M91: Upside Deal | N91: High | P91: Sean Royds | Q91: Wimpie Pieterse | R91: Product | S91: Cancelled to be ordered as complete SIP solution in next two weeks.
A92: ITSS Cisco LoB | B92: Concentrix | C92: Corporate | D92: OPP146994 | E92: 1077496.7 | F92: 53874.837 | G92: 53874.837 | H92: 0.05 | I92: Upside | J92: 46204 | K92: FY 27 Q2 | L92: No | M92: Upside Deal | N92: Medium | P92: Olden Pieterse | Q92: Wimpie Pieterse | R92: Product | S92: 11th Floor Auto Atlantic Bldg - Submitted quote
A93: ITSS Cisco LoB | B93: The Spar Group Ltd | C93: FSI & Retail | D93: OPP147073 | E93: 1056330 | F93: 1056330 | G93: 126759.6 | H93: 0.12 | I93: Commit | J93: 46143 | K93: FY 27 Q1 | L93: Yes | M93: Backlog Deal | N93: High | O93: Checked | P93: Olden Pieterse | Q93: Wimpie Pieterse | R93: Product | S93: EDD 4 May - 200 x MX67
A94: ITSS Cisco LoB | B94: Aspen SA Operations (Pty) Ltd | C94: Corporate | D94: OPP142307 | E94: 1046707.4 | F94: 1046707.4 | G94: 281222.63 | H94: 0.1 | I94: Upside | J94: 46235 | K94: FY 27 Q2 | L94: No | M94: Upside Deal | N94: High | O94: checked | P94: Roan van Nieuwenhuizen | Q94: Wimpie Pieterse | R94: Product | S94: Quote refreshed expiring end of May - Customer busy arranging PO
A95: ITSS Cisco LoB | B95: SANSA | C95: Public | D95: OPP145574 | E95: 1035000 | F95: 1035000 | G95: 103500 | H95: 0.1 | I95: Upside | J95: 46296 | K95: FY 27 Q3 | L95: No | M95: Upside Deal | N95: Low | O95: Checked | P95: Wandile Dlamini | Q95: Wimpie Pieterse | R95: Product | S95: EDD 120 days for the WLC - RFQ Wireless refresh
A96: ITSS Cisco LoB | B96: RCL Consumer - Group EOL refresh | C96: Corporate | D96: OPP144190_02 | E96: 1006059 | F96: 1006059 | G96: 100605.9 | H96: 0.1 | I96: Upside | J96: 46266 | K96: FY 27 Q2 | L96: No | M96: Upside Deal | N96: High | O96: Checked | P96: Hein Botha | Q96: Wimpie Pieterse | R96: Product
A97: ITSS Cisco LoB | B97: Aspen SA Operations (Pty) Ltd | C97: Corporate | D97: OPP144676 | E97: 965955.74 | F97: 965955.74 | G97: 96595.574 | H97: 0.1 | I97: Commit | J97: 46174 | K97: FY 27 Q1 | L97: No | M97: Backlog Deal | N97: High | O97: checked | P97: Roan van Nieuwenhuizen | Q97: Wimpie Pieterse | R97: Product | S97: EDD - 15 June 2026
A98: ITSS Cisco LoB | B98: Pioneer Foods (Pty) Ltd | C98: FSI & Retail | D98: OPP136577/03 | E98: 934980 | F98: 93498 | G98: 93498 | H98: 0.1 | I98: Commit | J98: 46204 | K98: FY 27 Q2 | L98: No | M98: Backlog Deal | N98: High | P98: Olden Pieterse | Q98: Wimpie Pieterse | R98: Product | S98: EDD May - Ceres Beverages - order received
A99: ITSS Cisco LoB | B99: Concentrix Cvg South Africa | C99: Corporate | D99: OPP142082 | E99: 917255.58 | F99: 917255.58 | G99: 55035.335 | H99: 0.06 | I99: Commit | J99: 46174 | K99: FY 27 Q1 | L99: No | M99: Backlog Deal | N99: High | P99: Olden Pieterse | Q99: Wimpie Pieterse | R99: Product
A100: ITSS Cisco LoB | B100: Concentrix Cvg South Africa | C100: Corporate | D100: OPP142083 | E100: 917255.58 | F100: 917255.58 | G100: 55035.335 | H100: 0.06 | I100: Commit | J100: 46174 | K100: FY 27 Q1 | L100: No | M100: Backlog Deal | N100: High | P100: Olden Pieterse | Q100: Wimpie Pieterse | R100: Product
...

Sheet Add to Cadence
A1: LOB INPUT
D2: Totals | E2: =SUM(E4:E161996) -> 0 | F2: =SUM(F4:F161996) -> 0 | G2: =SUM(G4:G161996) -> 0
A3: LOB INPUT | B3: Customer Name | C3: Sales Vertical | D3: OPP Number | E3: Gross Revenue | F3: Expected Net Revenue | G3: GP Value | H3: GP % | I3: Deal Status | J3: Billing Month | K3: FY Qrt list | L3: Billing Status | M3: Source | N3: Deal Probability | O3: Extra Notes | P3: Presales Name | Q3: LOB / BDM Name | R3: Deal Type | S3: Update | T3: Medium high chase
A4: ITSS Cisco LoB | B4: ABB South Africa (Pty) Ltd | C4: Corporate | D4: OPP148431 | E4: R 421 128,38 | F4: R 421 128,39 | H4: 0.1 | I4: Upside | J4: 46266 | L4: No | M4: Upside Deal | N4: Medium | P4: Mason Hlongwane | Q4: Wes Beck | R4: Software / Licence | S4: waiting for response
K16: =IF(J16="","",_xlfn.XLOOKUP(J16,Lookup!E:E,Lookup!F:F))
K17: =IF(J17="","",_xlfn.XLOOKUP(J17,Lookup!E:E,Lookup!F:F))
K18: =IF(J18="","",_xlfn.XLOOKUP(J18,Lookup!E:E,Lookup!F:F))
K19: =IF(J19="","",_xlfn.XLOOKUP(J19,Lookup!E:E,Lookup!F:F))
K20: =IF(J20="","",_xlfn.XLOOKUP(J20,Lookup!E:E,Lookup!F:F))
K21: =IF(J21="","",_xlfn.XLOOKUP(J21,Lookup!E:E,Lookup!F:F))
K22: =IF(J22="","",_xlfn.XLOOKUP(J22,Lookup!E:E,Lookup!F:F))
K23: =IF(J23="","",_xlfn.XLOOKUP(J23,Lookup!E:E,Lookup!F:F))
K24: =IF(J24="","",_xlfn.XLOOKUP(J24,Lookup!E:E,Lookup!F:F))
K25: =IF(J25="","",_xlfn.XLOOKUP(J25,Lookup!E:E,Lookup!F:F))
K26: =IF(J26="","",_xlfn.XLOOKUP(J26,Lookup!E:E,Lookup!F:F))
K27: =IF(J27="","",_xlfn.XLOOKUP(J27,Lookup!E:E,Lookup!F:F))
... K58: =IF(J58="","",_xlfn.XLOOKUP(J58,Lookup!E:E,Lookup!F:F))

Sheet SFDCVerify
B1: LOB INPUT | C1: Customer Name | D1: Sales Vertical | E1: OPP Number | F1: Gross Revenue | G1: Expected Net Revenue | H1: GP Value | I1: GP % | J1: Deal Status | K1: Billing Month | L1: FY Qrt list | M1: Billing Status | N1: Source | O1: Deal Probability | P1: Extra Notes | Q1: Presales Name
B2: ITSS Cisco Products | C2: South African Social Agency (SASSA) | D2: Lerato Maja | E2: OPP146677/06 | F2: 144390113 | H2: 7219505.7 | I2: 0.05 | J2: Upside | K2: 2029/10/01 | M2: No | N2: Proposal Submitted | O2: Low | Q2: David Ramorola
A3: Please remove this is not a ITSS Cisco OPP | B3: ITSS Cisco Products | C3: Alexander Forbes Group Services (PTY)LTD | D3: Nonhlanhla Chitura | E3: OPP138612 | F3: 75000000 | H3: 11250000 | I3: 0.15 | J3: Upside | K3: 2029/10/01 | M3: No | N3: Opportunity Created | O3: Medium
B4: ITSS Cisco Products | C4: Pep A Division Of Pepkor Trading (PTd | D4: Freddy Abrahams | E4: OPP145464 | F4: 67361615 | H4: 4715313.1 | I4: 0.07 | J4: Upside | K4: 2027/01/01 | M4: No | N4: Quote Created | O4: Low | Q4: Paul van Rooyen
B5: ITSS Cisco Products | C5: Eskom Holdings (SOC) Ltd | D5: Thuli Kgabo | E5: OPP114025/01 | F5: 65000000 | H5: 7800000 | I5: 0.12 | J5: Upside | K5: 2029/10/01 | M5: No | N5: Lead Generated | O5: Low
B6: ITSS Cisco Products | C6: Nedbank Limited | D6: Johan Marais | E6: OPP146707 | F6: 52689875 | H6: 1580696.2 | I6: 0.03 | J6: Upside | K6: 2027/02/01 | M6: No | N6: Opportunity Created | O6: Low
B7: ITSS Cisco Products | C7: Openserve (Pty) Ltd | D7: Estelle Van der Walt | E7: OPP141512/01 | F7: 36769778 | H7: 3676977.8 | I7: 0.1 | J7: Upside | K7: 2026/09/01 | M7: No | N7: Quote Created | O7: Low | Q7: Johan Taljaard
B8: ITSS Cisco Products | C8: Airports Company South Africa (SOC) | D8: .Paballo Lehloma | E8: OPP143531/01 | F8: 34092194 | H8: 3409219.4 | I8: 0.1 | J8: Upside | K8: 2026/08/01 | M8: No | N8: Quote Created | O8: Low | Q8: Johan Taljaard; Wandile Dlamini; John Killian
B9: ITSS Cisco Products | C9: Openserve (Pty) Ltd | D9: Estelle Van der Walt | E9: OPP148228/01 | F9: 30000000 | H9: 3000000 | I9: 0.1 | J9: Upside | K9: 2026/09/01 | M9: No | N9: Opportunity Created | O9: Low
A10: Valid Opp Low win probeblity | B10: ITSS Cisco Products | C10: Telkom Consumer | D10: Bongani Nhlanzi | E10: OPP134434 | F10: 29034060 | H10: 2903406 | I10: 0.1 | J10: Upside | K10: 2026/09/01 | M10: No | N10: Proposal Submitted | O10: Low | Q10: Johan Taljaard
B11: ITSS Cisco Products | C11: State Information Technology AgencyLtd | D11: John Croone | E11: OPP139035 | F11: 25012131 | H11: 2501213.1 | I11: 0.1 | J11: Upside | K11: 2026/10/01 | M11: No | N11: Proposal Submitted | O11: Medium | Q11: David Ramorola
B12: ITSS Cisco Products | C12: Nedbank Limited | D12: Johan Marais | E12: OPP132268 | F12: 24713987 | H12: 2471398.7 | I12: 0.1 | J12: Upside | K12: 2027/03/01 | M12: No | N12: Proposal Created | O12: Medium | Q12: Sean Royds
A13: Please remove, Already in cadence | B13: ITSS Cisco Products | C13: Openserve (Pty) Ltd | D13: Estelle Van der Walt | E13: OPP145768/01 | F13: 21938053 | H13: 2193805.3 | I13: 0.1 | J13: Upside | K13: 2026/08/01 | M13: No | N13: Quote Created | O13: Low | Q13: Johan Taljaard
B14: ITSS Cisco Products | C14: Nedbank Limited | D14: Johan Marais | E14: OPP125805 | F14: 19863301 | H14: 1191798 | I14: 0.06 | J14: Upside | K14: 2026/06/01 | M14: No | N14: Opportunity Qualified | O14: Low | Q14: Sean Royds
B15: ITSS Cisco Products | C15: Mr Price Group Limited | D15: Dinesh Maharaj | E15: OPP139787 | F15: 18602487 | H15: 744099.46 | I15: 0.04 | J15: Upside | K15: 2026/08/01 | M15: No | N15: Awaiting Customer Decision | O15: Low | Q15: Roan van Nieuwenhuizen
B16: ITSS Cisco Products | C16: Human Settlements | D16: Zodwa Ntshangase | E16: OPP140895/01 | F16: 17503044 | H16: 875152.18 | I16: 0.05 | J16: Upside | K16: 2026/09/01 | M16: No | N16: Quote Created | O16: Low | Q16: David Ramorola; Hanno Oosthuisen
B17: ITSS Cisco Products | C17: Life Healthcare Group (Pty) Ltd | D17: Melissa Cloete | E17: OPP144429 | F17: 15072048 | H17: 1808645.8 | I17: 0.12 | J17: Upside | K17: 2026/09/01 | M17: No | N17: Proposal Created | O17: Low | Q17: Wandile Dlamini
B18: ITSS Cisco Products | C18: AVI Financial Services (Pty) Ltd | D18: Andre Erasmus | E18: OPP125425/04 | F18: 15000000 | H18: 750000 | I18: 0.05 | J18: Upside | K18: 2027/11/01 | M18: No | N18: Products identified | O18: Low
B19: ITSS Cisco Products | C19: South African Reserve Bank | D19: .Paballo Lehloma | E19: OPP144770/01 | F19: 15000000 | H19: 1050000 | I19: 0.07 | J19: Upside | K19: 2027/03/01 | M19: No | N19: Products identified | O19: Medium
A20: Valid Opp Low win probeblity | B20: ITSS Cisco Products | C20: Telkom Consumer | D20: Bongani Nhlanzi | E20: OPP143239 | F20: 14550816 | H20: 1746097.9 | I20: 0.12 | J20: Upside | K20: 2026/06/01 | M20: No | N20: Quote Created | O20: Low
B21: ITSS Cisco Products | C21: Pep A Division Of Pepkor Trading (PTd | D21: Freddy Abrahams | E21: OPP135155 | F21: 11735414 | H21: 821479.01 | I21: 0.07 | J21: Upside | K21: 2026/11/01 | M21: No | N21: Quote Created | O21: Low | Q21: Paul van Rooyen; Roan van Nieuwenhuizen
B22: ITSS Cisco Products | C22: Electoral Commission of SouthAfrica Iec | D22: John Croone | E22: OPP139758/03 | F22: 10809716 | H22: 1621457.4 | I22: 0.15 | J22: Commit | K22: 2026/09/01 | M22: No | N22: Shortlist/Verbal Commitment/Awaiting Client PO | O22: High

Sheet BCX Internal
A1: LOB INPUT | B1: Customer Name | C1: Sales Vertical | D1: OPP Number | E1: Gross Revenue | F1: Expected Net Revenue | G1: GP Value | H1: GP % | I1: Deal Status | J1: Billing Month | L1: Billing Status | M1: Source | N1: Deal Probability | O1: Extra Notes | P1: Presales Name | Q1: LOB / BDM Name | R1: Deal Type | S1: Update | T1: FY Qrt list | U1: Medium high chase
A2: ITSS Cisco LoB | B2: BCX DC & Core | C2: Mining Indust&Health | D2: BCX Internal | E2: 28276225 | F2: 0 | G2: 0 | H2: 0 | J2: 46296 | L2: No | M2: Upside Deal | N2: Low | O2: Checked | P2: Johan Taljaard | Q2: Wimpie Pieterse | R2: Product | S2: BCX spine refresh
A3: ITSS Cisco LoB | B3: BCX Concom | C3: Mining Indust&Health | D3: BCX Internal | E3: 6957253 | F3: 0 | G3: 0 | H3: 0 | J3: 46296 | L3: No | M3: Upside Deal | N3: Low | O3: Checked | P3: Johan Taljaard | Q3: Wimpie Pieterse | R3: Software / Licence | S3: Secure Connect Licensing
A4: ITSS Cisco LoB | B4: BCX DC & Core | C4: Mining Indust&Health | D4: BCX Internal | E4: 3710083 | F4: 0 | G4: 0 | H4: 0 | J4: 46296 | L4: No | M4: Upside Deal | N4: Medium | O4: Checked | P4: Johan Taljaard | Q4: Wimpie Pieterse | R4: OEM Service | S4: Cisco prof service APIC and MSO
A5: ITSS Cisco LoB | B5: BCX Concom | C5: Mining Indust&Health | D5: BCX Internal | E5: 5225742.3 | F5: 0 | G5: 0 | H5: 0 | J5: 46174 | L5: No | M5: Backlog Deal | N5: High | O5: Checked | P5: Johan Taljaard | Q5: Wimpie Pieterse | R5: Software / Licence | S5: Meraki licenses
A6: ITSS Cisco LoB | B6: BCX DC & Core | C6: Mining Indust&Health | D6: BCX Internal | E6: 2359798 | F6: 0 | G6: 0 | H6: 0 | J6: 46296 | L6: No | M6: Upside Deal | N6: Medium | O6: Checked | P6: Johan Taljaard | Q6: Wimpie Pieterse | R6: Product | S6: APIC refresh
A7: ITSS Cisco LoB | B7: BCX Wifi | C7: Mining Indust&Health | D7: BCX Internal | E7: 1771002 | F7: 0 | G7: 0 | H7: 0 | J7: 46174 | L7: No | M7: Backlog Deal | N7: High | O7: Checked | P7: Johan Taljaard | Q7: Wimpie Pieterse | R7: Product | S7: BCX Wifi AP's - Approved by SRC
A8: ITSS Cisco LoB | B8: Telkom SA SOC Limited | C8: Mining Indust&Health | D8: BCX Internal | E8: 49992166 | F8: 0 | G8: 0 | H8: 1 | J8: 46204 | K8: FY 27 Q1 | L8: No | M8: Backlog Deal | N8: High | O8: checked | P8: johan Taljaard | Q8: Wimpie Pieterse | R8: OEM Service | S8: BCX SFC Year 3/3

Sheet Monitor status

Sheet Noted losses
A1: LOB INPUT
D2: Totals | E2: =SUM(E4:E161992) -> 1334045 | F2: =SUM(F4:F161992) -> 1334045 | G2: =SUM(G4:G161992) -> 160085.4
A3: LOB INPUT | B3: Customer Name | C3: Sales Vertical | D3: OPP Number | E3: Gross Revenue | F3: Expected Net Revenue | G3: GP Value | H3: GP % | I3: Deal Status | J3: Billing Month | K3: FY Qrt list | L3: Billing Status | M3: Source | N3: Deal Probability | O3: Extra Notes | P3: Presales Name | Q3: LOB / BDM Name | R3: Deal Type | S3: Update | T3: Medium high chase
A4: ITSS Cisco LoB | B4: Momentum Metropolitan Life Ltd Metropolitan | C4: FSI & Retail | D4: OPP146912 | E4: 1334045 | F4: 1334045 | G4: 160085.4 | H4: 0.12 | I4: Upside | J4: 46266 | K4: FY 27 Q2 | L4: No | M4: Upside Deal | N4: High | P4: Wandile Dlamini | Q4: Wimpie Pieterse | R4: Product | S4: CUSTOMER DECIDED TO GO WITH ANOTHER SOLUTION BECAUSE OF LEAD TIMES

Sheet DealDefinitions
B2: Deal Status | C2: Source | D2: Deal Probability | E2: Definition | F2: Risk Factors
B3: Commit | C3: Backlog Deal | D3: No Risk | E3: Historical month consolidated | F3: None - Money in the bank
B4: Commit | C4: Backlog Deal | D4: High | E4: PO placed on OEM/ Supplier | F4: Timing to invoice/ Recognise
B5: Commit | C5: Commit | D5: High | E5: Award letter/ Written commitement - no PO | F5: Timing to PO
B6: Upside | C6: Upside | D6: High | E6: Verbal commitment/ Very high confidence | F6: Competition/ Timing
B7: Upside | C7: Upside | D7: Medium | E7: No customer commitment/incumbancy/Medium to High confidence | F7: Competition/ Cancellation
B8: Upside | C8: Upside | D8: Low | E8: Tender/ Medium to Low confidence | F8: Competition/ Cancellation

Sheet Cisco view
A1: LOB INPUT
D2: Totals | E2: =SUM(E4:E222) -> #REF!
A3: ='Current Cadence'!A3 -> LOB INPUT | B3: ='Current Cadence'!B3 -> Customer Name | C3: ='Current Cadence'!C3 -> Sales Vertical | D3: ='Current Cadence'!D3 -> OPP Number | E3: ='Current Cadence'!E3 -> Gross Revenue | F3: ='Current Cadence'!I3 -> Deal Status | G3: ='Current Cadence'!J3 -> Billing Month | H3: ='Current Cadence'!K3 -> FY Qrt list | I3: ='Current Cadence'!L3 -> Billing Status | J3: ='Current Cadence'!M3 -> Source | K3: ='Current Cadence'!N3 -> Deal Probability | L3: ='Current Cadence'!O3 -> Extra Notes | M3: ='Current Cadence'!P3 -> Presales Name | ... U3: ='Current Cadence'!X3 -> 0
A4: ='Current Cadence'!A4 -> ITSS Cisco LoB | B4: ='Current Cadence'!B4 -> South African Revenue Services | C4: ='Current Cadence'!C4 -> Public | D4: ='Current Cadence'!D4 -> OPP145398 | E4: ='Current Cadence'!E4 -> 2.4910934e+08 | F4: ='Current Cadence'!I4 -> Upside | G4: ='Current Cadence'!J4 -> 46447 | H4: ='Current Cadence'!K4 -> FY 27 Q4 | I4: ='Current Cadence'!L4 -> No | J4: ='Current Cadence'!M4 -> Upside Deal | K4: ='Current Cadence'!N4 -> Low | L4: ='Current Cadence'!O4 -> 0 | M4: ='Current Cadence'!P4 -> David Ramorola | ... U4: ='Current Cadence'!X4 -> 0
A5: ='Current Cadence'!A5 -> ITSS Cisco LoB | B5: ='Current Cadence'!B5 -> South African Social Agency (SASSA) | C5: ='Current Cadence'!C5 -> Public | D5: ='Current Cadence'!D5 -> OPP146677 | E5: ='Current Cadence'!E5 -> 1.235666e+08 | F5: ='Current Cadence'!I5 -> Upside | G5: ='Current Cadence'!J5 -> 46447 | H5: ='Current Cadence'!K5 -> FY 27 Q4 | I5: ='Current Cadence'!L5 -> No | J5: ='Current Cadence'!M5 -> Upside Deal | K5: ='Current Cadence'!N5 -> Low | L5: ='Current Cadence'!O5 -> 0 | M5: ='Current Cadence'!P5 -> David Ramorola | ... O5: ='Current Cadence'!R5 -> Product | P5: Howard to checkup with Viloshnee on next steps | Q5: ='Current Cadence'!T5 -> 0 | R5: ='Current Cadence'!U5 -> 0 | S5: ='Current Cadence'!V5 -> 0 | T5: ='Current Cadence'!W5 -> 0 | U5: ='Current Cadence'!X5 -> 0
A6: ='Current Cadence'!A6 -> ITSS Cisco LoB | B6: ='Current Cadence'!B6 -> The Spar Group Ltd | C6: ='Current Cadence'!C6 -> FSI & Retail | D6: ='Current Cadence'!D6 -> OPP136919 | E6: ='Current Cadence'!E6 -> 38123456 | F6: ='Current Cadence'!I6 -> Upside | G6: ='Current Cadence'!J6 -> 46174 | H6: ='Current Cadence'!K6 -> FY 27 Q1 | I6: ='Current Cadence'!L6 -> No | J6: ='Current Cadence'!M6 -> Upside Deal | K6: ='Current Cadence'!N6 -> High | L6: ='Current Cadence'!O6 -> checked | M6: ='Current Cadence'!P6 -> Roan van Nieuwenhuizen | ... U6: ='Current Cadence'!X6 -> 0
A7: ='Current Cadence'!A7 -> ITSS Cisco LoB | B7: ='Current Cadence'!B7 -> Telkom Consumer | C7: ='Current Cadence'!C7 -> Mining Indust&Health | D7: ='Current Cadence'!D7 -> OPP133098 | E7: ='Current Cadence'!E7 -> 33825197 | F7: ='Current Cadence'!I7 -> Commit | G7: ='Current Cadence'!J7 -> 46174 | H7: ='Current Cadence'!K7 -> FY 27 Q1 | I7: ='Current Cadence'!L7 -> No | J7: ='Current Cadence'!M7 -> Backlog Deal | K7: ='Current Cadence'!N7 -> High | L7: ='Current Cadence'!O7 -> checked | M7: ='Current Cadence'!P7 -> johan Taljaard | ... U7: ='Current Cadence'!X7 -> 0
A8: ='Current Cadence'!A8 -> ITSS Cisco LoB | B8: ='Current Cadence'!B8 -> Discovery Central Services (Pty) Ltd | C8: ='Current Cadence'!C8 -> FSI & Retail | D8: ='Current Cadence'!D8 -> OPP147096 | E8: ='Current Cadence'!E8 -> 30614619 | F8: ='Current Cadence'!I8 -> Upside | G8: ='Current Cadence'!J8 -> 46235 | H8: ='Current Cadence'!K8 -> FY 27 Q2 | I8: ='Current Cadence'!L8 -> No | J8: ='Current Cadence'!M8 -> Upside Deal | K8: ='Current Cadence'!N8 -> Low | L8: ='Current Cadence'!O8 -> checked | M8: ='Current Cadence'!P8 -> Paul van Rooyen | ... U8: ='Current Cadence'!X8 -> 0
A9: ='Current Cadence'!A9 -> ITSS Cisco LoB | B9: ='Current Cadence'!B9 -> Telkom ISP | C9: ='Current Cadence'!C9 -> Mining Indust&Health | D9: ='Current Cadence'!D9 -> OPP147364 | E9: ='Current Cadence'!E9 -> 28723558 | F9: ='Current Cadence'!I9 -> Upside | G9: ='Current Cadence'!J9 -> 46327 | H9: ='Current Cadence'!K9 -> FY 27 Q3 | I9: ='Current Cadence'!L9 -> No | J9: ='Current Cadence'!M9 -> Upside Deal | K9: ='Current Cadence'!N9 -> Medium | L9: ='Current Cadence'!O9 -> checked | M9: ='Current Cadence'!P9 -> Johan Taljaard | ... U9: ='Current Cadence'!X9 -> 0
A10: ='Current Cadence'!A10 -> ITSS Cisco LoB | B10: ='Current Cadence'!B10 -> Openserve | C10: ='Current Cadence'!C10 -> Mining Indust&Health | D10: ='Current Cadence'!D10 -> OPP145768 | E10: ='Current Cadence'!E10 -> 21938053 | F10: ='Current Cadence'!I10 -> Upside | G10: ='Current Cadence'!J10 -> 46327 | H10: ='Current Cadence'!K10 -> FY 27 Q3 | I10: ='Current Cadence'!L10 -> No | J10: ='Current Cadence'!M10 -> Upside Deal | K10: ='Current Cadence'!N10 -> Medium | L10: ='Current Cadence'!O10 -> checked | M10: ='Current Cadence'!P10 -> Johan Taljaard | ... U10: ='Current Cadence'!X10 -> 0
A11: ='Current Cadence'!A11 -> ITSS Cisco LoB | B11: ='Current Cadence'!B11 -> Telkom Consumer | C11: ='Current Cadence'!C11 -> Mining Indust&Health | D11: ='Current Cadence'!D11 -> OPP147259 | E11: ='Current Cadence'!E11 -> 21938052 | F11: ='Current Cadence'!I11 -> Upside | G11: ='Current Cadence'!J11 -> 46327 | H11: ='Current Cadence'!K11 -> FY 27 Q3 | I11: ='Current Cadence'!L11 -> No | J11: ='Current Cadence'!M11 -> Upside Deal | K11: ='Current Cadence'!N11 -> Low | L11: ='Current Cadence'!O11 -> checked | M11: ='Current Cadence'!P11 -> Johan Taljaard | ... U11: ='Current Cadence'!X11 -> 0
A12: ='Current Cadence'!A12 -> ITSS Cisco LoB | B12: ='Current Cadence'!B12 -> The Standard Bank of South Africa | C12: ='Current Cadence'!C12 -> FSI & Retail | D12: ='Current Cadence'!D12 -> OPP13777 | E12: ='Current Cadence'!E12 -> 17211644 | F12: ='Current Cadence'!I12 -> Commit | G12: ='Current Cadence'!J12 -> 46478 | H12: ='Current Cadence'!K12 | I12: ='Current Cadence'!L12 -> No | J12: ='Current Cadence'!M12 -> Backlog Deal | K12: ='Current Cadence'!N12 -> High | L12: ='Current Cadence'!O12 -> Checked | M12: ='Current Cadence'!P12 -> Paul van Rooyen | ... U12: ='Current Cadence'!X12 -> 0
A13: ='Current Cadence'!A13 -> ITSS Cisco LoB | B13: ='Current Cadence'!B13 -> Telkom Consumer | C13: ='Current Cadence'!C13 -> Mining Indust&Health | D13: ='Current Cadence'!D13 -> OPP135119/01 | E13: ='Current Cadence'!E13 -> 15799289 | F13: ='Current Cadence'!I13 -> Upside | G13: ='Current Cadence'!J13 -> 46327 | H13: ='Current Cadence'!K13 -> FY 27 Q3 | I13: ='Current Cadence'!L13 -> No | J13: ='Current Cadence'!M13 -> Upside Deal | K13: ='Current Cadence'!N13 -> Medium | L13: ='Current Cadence'!O13 -> checked | M13: ='Current Cadence'!P13 -> Johan Taljaard | ... U13: ='Current Cadence'!X13 -> 0
A14: ='Current Cadence'!A14 -> ITSS Cisco LoB | B14: ='Current Cadence'!B14 -> Openserve | C14: ='Current Cadence'!C14 -> Mining Indust&Health | D14: ='Current Cadence'!D14 -> OPP141512/01 | E14: ='Current Cadence'!E14 -> 14895000 | F14: ='Current Cadence'!I14 -> Upside | G14: ='Current Cadence'!J14 -> 46327 | H14: ='Current Cadence'!K14 -> FY 27 Q3 | I14: ='Current Cadence'!L14 -> No | J14: ='Current Cadence'!M14 -> Upside Deal | K14: ='Current Cadence'!N14 -> Medium | L14: ='Current Cadence'!O14 -> checked | M14: ='Current Cadence'!P14 -> Johan Taljaard | ... U14: ='Current Cadence'!X14 -> 0
A15: ='Current Cadence'!A15 -> ITSS Cisco LoB | B15: ='Current Cadence'!B15 -> SANBS | C15: ='Current Cadence'!C15 -> Public | D15: ='Current Cadence'!D15 -> OPP146783 | E15: ='Current Cadence'!E15 -> 14433451 | F15: ='Current Cadence'!I15 -> Upside | G15: ='Current Cadence'!J15 -> 46296 | H15: ='Current Cadence'!K15 -> FY 27 Q3 | I15: ='Current Cadence'!L15 -> No | J15: ='Current Cadence'!M15 -> Upside Deal | K15: ='Current Cadence'!N15 -> Low | L15: ='Current Cadence'!O15 -> Checked | M15: ='Current Cadence'!P15 -> Wandile Dlamini | ... U15: ='Current Cadence'!X15 -> 0
A16: ='Current Cadence'!A16 -> ITSS Cisco LoB | B16: ='Current Cadence'!B16 -> Nedbank Limited | C16: ='Current Cadence'!C16 -> FSI & Retail | D16: ='Current Cadence'!D16 -> OPP147252 | E16: ='Current Cadence'!E16 -> 14378595 | F16: ='Current Cadence'!I16 -> Upside | G16: ='Current Cadence'!J16 -> 46266 | H16: ='Current Cadence'!K16 -> FY 27 Q2 | I16: ='Current Cadence'!L16 -> No | J16: ='Current Cadence'!M16 -> Upside Deal | K16: ='Current Cadence'!N16 -> Low | L16: ='Current Cadence'!O16 -> 0 | M16: ='Current Cadence'!P16 -> Sean Royds | ... U16: ='Current Cadence'!X16 -> 0
A17: ='Current Cadence'!A17 -> ITSS Cisco LoB | B17: ='Current Cadence'!B17 -> Openserve (Pty) Ltd | C17: ='Current Cadence'!C17 -> Mining Indust&Health | D17: ='Current Cadence'!D17 -> OPP145588 | E17: ='Current Cadence'!E17 -> 13312345 | F17: ='Current Cadence'!I17 -> Upside | G17: ='Current Cadence'!J17 -> 46174 | H17: ='Current Cadence'!K17 -> FY 27 Q1 | I17: ='Current Cadence'!L17 -> No | J17: ='Current Cadence'!M17 -> Upside Deal | K17: ='Current Cadence'!N17 -> High | L17: ='Current Cadence'!O17 -> checked | M17: ='Current Cadence'!P17 -> Johan Taljaard | ... U17: ='Current Cadence'!X17 -> 0
... A19: ='Current Cadence'!A19 -> ITSS Cisco LoB | B19: ='Current Cadence'!B19 -> Telkom | C19: ='Current Cadence'!C19 -> Mining Indust&Health | D19: ='Current Cadence'!D19 -> OPP135119 | E19: ='Current Cadence'!E19 -> 13162789 | F19: ='Current Cadence'!I19 -> Upside | G19: ='Current Cadence'!J19 -> 46327 | H19: ='Current Cadence'!K19 -> FY 27 Q3 | I19: ='Current Cadence'!L19 -> No | J19: ='Current Cadence'!M19 -> Upside Deal | K19: ='Current Cadence'!N19 -> Medium | L19: ='Current Cadence'!O19 -> checked | M19: ='Current Cadence'!P19 -> Johan Taljaard | ... U19: ='Current Cadence'!X19 -> 0
A20: ='Current Cadence'!#REF! -> #REF! | B20: ='Current Cadence'!#REF! -> #REF! | C20: ='Current Cadence'!#REF! -> #REF! | D20: ='Current Cadence'!#REF! -> #REF! | E20: ='Current Cadence'!#REF! -> #REF! | F20: ='Current Cadence'!#REF! -> #REF! | G20: ='Current Cadence'!#REF! -> #REF! | H20: ='Current Cadence'!#REF! -> #REF! | ... U20: ='Current Cadence'!#REF! -> #REF!
A21: ='Current Cadence'!A20 -> ITSS Cisco LoB | B21: ='Current Cadence'!B20 -> Telkom Consumer | C21: ='Current Cadence'!C20 -> Mining Indust&Health | D21: ='Current Cadence'!D20 -> OPP142649/02 | E21: ='Current Cadence'!E20 -> 13140597 | F21: ='Current Cadence'!I20 -> Upside | G21: ='Current Cadence'!J20 -> 46327 | H21: ='Current Cadence'!K20 -> FY 27 Q3 | I21: ='Current Cadence'!L20 -> No | J21: ='Current Cadence'!M20 -> Upside Deal | K21: ='Current Cadence'!N20 -> Medium | L21: ='Current Cadence'!O20 -> checked | M21: ='Current Cadence'!P20 -> Johan Taljaard | ... U21: ='Current Cadence'!X20 -> 0
A22: ='Current Cadence'!A21 -> ITSS Cisco LoB | B22: ='Current Cadence'!B21 -> Openserve | C22: ='Current Cadence'!C21 -> Mining Indust&Health | D22: ='Current Cadence'!D21 -> OPP148548 | E22: ='Current Cadence'!E21 -> 12449770 | F22: ='Current Cadence'!I21 -> Upside | G22: ='Current Cadence'!J21 -> 46327 | H22: ='Current Cadence'!K21 -> FY 27 Q3 | I22: ='Current Cadence'!L21 -> No | J22: ='Current Cadence'!M21 -> Upside Deal | K22: ='Current Cadence'!N21 -> Medium | L22: ='Current Cadence'!O21 -> OPP148548 Openserve SPINE Switches - Tygerburg & Core | M22: ='Current Cadence'!P21 -> Johan Taljaard | ... U22: ='Current Cadence'!X21 -> 0
A23: ='Current Cadence'!A22 -> ITSS Cisco LoB | B23: ='Current Cadence'!B22 -> Air Traffic and Navigation ServicesCompany Limited | C23: ='Current Cadence'!C22 -> Public | D23: ='Current Cadence'!D22 -> OPP123907 | E23: ='Current Cadence'!E22 -> 12000000 | F23: ='Current Cadence'!I22 -> Upside | G23: ='Current Cadence'!J22 -> 46447 | H23: ='Current Cadence'!K22 -> FY 27 Q4 | I23: ='Current Cadence'!L22 -> No | J23: ='Current Cadence'!M22 -> Upside Deal | K23: ='Current Cadence'!N22 -> Low | L23: ='Current Cadence'!O22 -> Checked | M23: ='Current Cadence'!P22 -> Wandile Dlamini | ... U23: ='Current Cadence'!X22 -> 0
A24: ='Current Cadence'!#REF! -> #REF! | B24: ='Current Cadence'!#REF! -> #REF! | C24: ='Current Cadence'!#REF! -> #REF! | D24: ='Current Cadence'!#REF! -> #REF! | E24: ='Current Cadence'!#REF! -> #REF! | F24: ='Current Cadence'!#REF! -> #REF! | G24: ='Current Cadence'!#REF! -> #REF! | H24: ='Current Cadence'!#REF! -> #REF! | ... U24: ='Current Cadence'!#REF! -> #REF!
A25: ='Current Cadence'!A23 -> ITSS Cisco LoB | B25: ='Current Cadence'!B23 -> Telkom SA SOC Limited | C25: ='Current Cadence'!C23 -> Mining Indust&Health | D25: ='Current Cadence'!D23 -> OPP122332/04 | E25: ='Current Cadence'!E23 -> 11391262 | F25: ='Current Cadence'!I23 -> Commit | G25: ='Current Cadence'!J23 -> 46204 | H25: ='Current Cadence'!K23 -> FY 27 Q2 | I25: ='Current Cadence'!L23 -> No | J25: ='Current Cadence'!M23 -> Backlog Deal | K25: ='Current Cadence'!N23 -> High | L25: ='Current Cadence'!O23 -> checked | M25: ='Current Cadence'!P23 -> johan Taljaard | ... U25: ='Current Cadence'!X23 -> 0
A26: ='Current Cadence'!#REF! -> #REF! | B26: ='Current Cadence'!#REF! -> #REF! | C26: ='Current Cadence'!#REF! -> #REF! | D26: ='Current Cadence'!#REF! -> #REF! | E26: ='Current Cadence'!#REF! -> #REF! | F26: ='Current Cadence'!#REF! -> #REF! | G26: ='Current Cadence'!#REF! -> #REF! | H26: ='Current Cadence'!#REF! -> #REF! | ... U26: ='Current Cadence'!#REF! -> #REF!
A27: ='Current Cadence'!A24 -> ITSS Cisco LoB | B27: ='Current Cadence'!B24 -> Western Cape Government Health | C27: ='Current Cadence'!C24 -> Public | D27: ='Current Cadence'!D24 -> OPP140607 | E27: ='Current Cadence'!E24 -> 10854175 | F27: ='Current Cadence'!I24 -> Upside | G27: ='Current Cadence'!J24 -> 46296 | H27: ='Current Cadence'!K24 -> FY 27 Q3 | I27: ='Current Cadence'!L24 -> No | J27: ='Current Cadence'!M24 -> Upside Deal | K27: ='Current Cadence'!N24 -> Low | L27: ='Current Cadence'!O24 -> Checked | M27: ='Current Cadence'!P24 -> Wandile Dlamini | ... U27: ='Current Cadence'!X24 -> 0
A28: ='Current Cadence'!A25 -> ITSS Cisco LoB | B28: ='Current Cadence'!B25 -> Telkom Consumer | C28: ='Current Cadence'!C25 -> Mining Indust&Health | D28: ='Current Cadence'!D25 -> OPP142649/01 | E28: ='Current Cadence'!E25 -> 10827243 | F28: ='Current Cadence'!I25 -> Upside | G28: ='Current Cadence'!J25 -> 46327 | H28: ='Current Cadence'!K25 -> FY 27 Q3 | I28: ='Current Cadence'!L25 -> No | J28: ='Current Cadence'!M25 -> Upside Deal | K28: ='Current Cadence'!N25 -> Medium | L28: ='Current Cadence'!O25 -> checked | M28: ='Current Cadence'!P25 -> Johan Taljaard | ... U28: ='Current Cadence'!X25 -> 0
A29: ='Current Cadence'!A26 -> ITSS Cisco LoB | B29: ='Current Cadence'!B26 -> Tiger Brands | C29: ='Current Cadence'!C26 -> FSI & Retail | D29: ='Current Cadence'!D26 -> OPP138466 | E29: ='Current Cadence'!E26 -> 10753040 | F29: ='Current Cadence'!I26 -> Upside | G29: ='Current Cadence'!J26 -> 46204 | H29: ='Current Cadence'!K26 -> FY 27 Q2 | I29: ='Current Cadence'!L26 -> No | J29: ='Current Cadence'!M26 -> Upside Deal | K29: ='Current Cadence'!N26 -> Low | L29: ='Current Cadence'!O26 -> Checked | M29: ='Current Cadence'!P26 -> Nowell Duze | ... U29: ='Current Cadence'!X26 -> 0
A30: ='Current Cadence'!A27 -> ITSS Cisco LoB | B30: ='Current Cadence'!B27 -> Pep A Division Of Pepkor Trading (PTd | C30: ='Current Cadence'!C27 -> Corporate | D30: ='Current Cadence'!D27 -> OPP146179 | E30: ='Current Cadence'!E27 -> 8123456 | F30: ='Current Cadence'!I27 -> Upside | G30: ='Current Cadence'!J27 -> 46327 | H30: ='Current Cadence'!K27 -> FY 27 Q3 | I30: ='Current Cadence'!L27 -> No | J30: ='Current Cadence'!M27 -> Upside Deal | K30: ='Current Cadence'!N27 -> High | L30: ='Current Cadence'!O27 -> checked | M30: ='Current Cadence'!P27 -> Roan van Nieuwenhuizen | ... U30: ='Current Cadence'!X27 -> 0
A31: ='Current Cadence'!#REF! -> #REF! | B31: ='Current Cadence'!#REF! -> #REF! | C31: ='Current Cadence'!#REF! -> #REF! | D31: ='Current Cadence'!#REF! -> #REF! | E31: ='Current Cadence'!#REF! -> #REF! | F31: ='Current Cadence'!#REF! -> #REF! | G31: ='Current Cadence'!#REF! -> #REF! | H31: ='Current Cadence'!#REF! -> #REF! | ... U31: ='Current Cadence'!#REF! -> #REF!
A32: ='Current Cadence'!A28 -> ITSS Cisco LoB | B32: ='Current Cadence'!B28 -> Durban ICC | C32: ='Current Cadence'!C28 -> Public | D32: ='Current Cadence'!D28 -> OPP145736 | E32: ='Current Cadence'!E28 -> 7845333 | F32: ='Current Cadence'!I28 -> Upside | G32: ='Current Cadence'!J28 -> 46266 | H32: ='Current Cadence'!K28 -> FY 27 Q2 | I32: ='Current Cadence'!L28 -> No | J32: ='Current Cadence'!M28 -> Upside Deal | K32: ='Current Cadence'!N28 -> Medium | L32: ='Current Cadence'!O28 -> Checked | M32: ='Current Cadence'!P28 -> Wandile Dlamini | ... U32: ='Current Cadence'!X28 -> 0
A33: ='Current Cadence'!A29 -> ITSS Cisco LoB | B33: ='Current Cadence'!B29 -> Volkswagen Group Africa (Pty) Ltd | C33: ='Current Cadence'!C29 -> Corporate | D33: ='Current Cadence'!D29 -> OPP148038 | E33: ='Current Cadence'!E29 -> 7461453 | F33: ='Current Cadence'!I29 -> Upside | G33: ='Current Cadence'!J29 -> 46235 | H33: ='Current Cadence'!K29 -> FY 27 Q2 | I33: ='Current Cadence'!L29 -> No | J33: ='Current Cadence'!M29 -> Upside Deal | K33: ='Current Cadence'!N29 -> Low | L33: ='Current Cadence'!O29 -> 0 | M33: ='Current Cadence'!P29 -> Roan van Nieuwenhuizen | ... U33: ='Current Cadence'!X29 -> 0
A34: ='Current Cadence'!A30 -> ITSS Cisco LoB | B34: ='Current Cadence'!B30 -> Electoral Commission of SouthAfrica Iec | C34: ='Current Cadence'!C30 -> Public | D34: ='Current Cadence'!D30 -> OPP147418 | E34: ='Current Cadence'!E30 -> 7405205 | F34: ='Current Cadence'!I30 -> Upside | G34: ='Current Cadence'!J30 -> 46266 | H34: ='Current Cadence'!K30 -> FY 27 Q2 | I34: ='Current Cadence'!L30 -> No | J34: ='Current Cadence'!M30 -> Upside Deal | K34: ='Current Cadence'!N30 -> Low | L34: ='Current Cadence'!O30 -> 0 | M34: ='Current Cadence'!P30 -> Roan van Nieuwenhuizen | ... U34: ='Current Cadence'!X30 -> 0
A35: ='Current Cadence'!A31 -> ITSS Cisco LoB | B35: ='Current Cadence'!B31 -> Electoral Commission of SouthAfrica Iec | C35: ='Current Cadence'!C31 -> Public | D35: ='Current Cadence'!D31 -> OPP139758 | E35: ='Current Cadence'!E31 -> 7056976.2 | F35: ='Current Cadence'!I31 -> Commit | G35: ='Current Cadence'!J31 -> 46235 | H35: ='Current Cadence'!K31 -> FY 27 Q2 | I35: ='Current Cadence'!L31 -> No | J35: ='Current Cadence'!M31 -> Backlog Deal | K35: ='Current Cadence'!N31 -> High | L35: ='Current Cadence'!O31 -> Checked | M35: ='Current Cadence'!P31 -> David Ramorola | ... U35: ='Current Cadence'!X31 -> 0
A36: ='Current Cadence'!A32 -> ITSS Cisco LoB | B36: ='Current Cadence'!B32 -> Pep A Division Of Pepkor Trading (PTd | C36: ='Current Cadence'!C32 -> Corporate | D36: ='Current Cadence'!D32 -> OPP141566 | E36: ='Current Cadence'!E32 -> 6991803.2 | F36: ='Current Cadence'!I32 -> Upside | G36: ='Current Cadence'!J32 -> 46419 | H36: ='Current Cadence'!K32 -> FY 27 Q4 | I36: ='Current Cadence'!L32 -> No | J36: ='Current Cadence'!M32 -> Upside Deal | K36: ='Current Cadence'!N32 -> Medium | L36: ='Current Cadence'!O32 -> checked | M36: ='Current Cadence'!P32 -> Paul van Rooyen | ... U36: ='Current Cadence'!X32 -> 0
A37: ='Current Cadence'!A33 -> ITSS Cisco LoB | B37: ='Current Cadence'!B33 -> Nedbank Limited | C37: ='Current Cadence'!C33 -> FSI & Retail | D37: ='Current Cadence'!D33 -> OPP147043 | E37: ='Current Cadence'!E33 -> 5790700.2 | F37: ='Current Cadence'!I33 -> Commit | G37: ='Current Cadence'!J33 -> 46204 | H37: ='Current Cadence'!K33 -> FY 27 Q2 | I37: ='Current Cadence'!L33 -> No | J37: ='Current Cadence'!M33 -> Backlog Deal | K37: ='Current Cadence'!N33 -> High | L37: ='Current Cadence'!O33 -> 0 | M37: ='Current Cadence'!P33 -> Sean Royds | ... U37: ='Current Cadence'!X33 -> 0
A38: ='Current Cadence'!A34 -> ITSS Cisco LoB | B38: ='Current Cadence'!B34 -> Volkswagen Group Africa (Pty) Ltd | C38: ='Current Cadence'!C34 -> Corporate | D38: ='Current Cadence'!D34 -> OPP146486 | E38: ='Current Cadence'!E34 -> 5751314 | F38: ='Current Cadence'!I34 -> Upside | G38: ='Current Cadence'!J34 -> 46235 | H38: ='Current Cadence'!K34 -> FY 27 Q2 | I38: ='Current Cadence'!L34 -> No | J38: ='Current Cadence'!M34 -> Upside Deal | K38: ='Current Cadence'!N34 -> Low | L38: ='Current Cadence'!O34 -> 0 | M38: ='Current Cadence'!P34 -> Roan van Nieuwenhuizen | ... U38: ='Current Cadence'!X34 -> 0
A39: ='Current Cadence'!A35 -> ITSS Cisco LoB | B39: ='Current Cadence'!B35 -> Capitec Bank Limited | C39: ='Current Cadence'!C35 -> FSI & Retail | D39: ='Current Cadence'!D35 -> OPP089485 | E39: ='Current Cadence'!E35 -> 5699203 | F39: ='Current Cadence'!I35 -> Commit | G39: ='Current Cadence'!J35 -> 46327 | H39: ='Current Cadence'!K35 -> FY 27 Q3 | I39: ='Current Cadence'!L35 -> No | J39: ='Current Cadence'!M35 -> Backlog Deal | K39: ='Current Cadence'!N35 -> High | L39: ='Current Cadence'!O35 -> checked | M39: ='Current Cadence'!P35 -> Paul van Rooyen | ... U39: ='Current Cadence'!X35 -> 0
A40: ='Current Cadence'!A36 -> ITSS Cisco LoB | B40: ='Current Cadence'!B36 -> Tiger Brands | C40: ='Current Cadence'!C36 -> FSI & Retail | D40: ='Current Cadence'!D36 -> OPP146660 | E40: ='Current Cadence'!E36 -> 5301769.3 | F40: ='Current Cadence'!I36 -> Upside | G40: ='Current Cadence'!J36 -> 46204 | H40: ='Current Cadence'!K36 -> FY 27 Q2 | I40: ='Current Cadence'!L36 -> No | J40: ='Current Cadence'!M36 -> Upside Deal | K40: ='Current Cadence'!N36 -> Low | L40: ='Current Cadence'!O36 -> Checked | M40: ='Current Cadence'!P36 -> Nowell Duze | ... U40: ='Current Cadence'!X36 -> 0
A41: ='Current Cadence'!A37 -> ITSS Cisco LoB | B41: ='Current Cadence'!B37 -> Momentum Metropolitan Life Ltd Metropolitan | C41: ='Current Cadence'!C37 -> FSI & Retail | D41: ='Current Cadence'!D37 -> OPP142558 | E41: ='Current Cadence'!E37 -> 5238762.6 | F41: ='Current Cadence'!I37 -> Commit | G41: ='Current Cadence'!J37 -> 46143 | H41: ='Current Cadence'!K37 -> FY 27 Q1 | I41: ='Current Cadence'!L37 -> Yes | J41: ='Current Cadence'!M37 -> Backlog Deal | K41: ='Current Cadence'!N37 -> High | L41: ='Current Cadence'!O37 -> Checked | M41: ='Current Cadence'!P37 -> Wandile Dlamini | ... U41: ='Current Cadence'!X37 -> 0
A42: ='Current Cadence'!A38 -> ITSS Cisco LoB | B42: ='Current Cadence'!B38 -> PepsiCo South Africa (Pty) Ltd | C42: ='Current Cadence'!C38 -> Corporate | D42: ='Current Cadence'!D38 -> OPP144981 | E42: ='Current Cadence'!E38 -> 4973229.5 | F42: ='Current Cadence'!I38 -> Upside | G42: ='Current Cadence'!J38 -> 46235 | H42: ='Current Cadence'!K38 -> FY 27 Q2 | I42: ='Current Cadence'!L38 -> No | J42: ='Current Cadence'!M38 -> Upside Deal | K42: ='Current Cadence'!N38 -> Medium | L42: ='Current Cadence'!O38 -> 0 | M42: ='Current Cadence'!P38 -> Olden Pieterse | ... U42: ='Current Cadence'!X38 -> 0
A43: ='Current Cadence'!#REF! -> #REF! | B43: ='Current Cadence'!#REF! -> #REF! | C43: ='Current Cadence'!#REF! -> #REF! | D43: ='Current Cadence'!#REF! -> #REF! | E43: ='Current Cadence'!#REF! -> #REF! | F43: ='Current Cadence'!#REF! -> #REF! | G43: ='Current Cadence'!#REF! -> #REF! | H43: ='Current Cadence'!#REF! -> #REF! | ... U43: ='Current Cadence'!#REF! -> #REF!
A44: ='Current Cadence'!A39 -> ITSS Cisco LoB | B44: ='Current Cadence'!B39 -> Sanlam Life Insurance Limited | C44: ='Current Cadence'!C39 -> FSI & Retail | D44: ='Current Cadence'!D39 -> OPP137867 | E44: ='Current Cadence'!E39 -> 4963898 | F44: ='Current Cadence'!I39 -> Upside | G44: ='Current Cadence'!J39 -> 46235 | H44: ='Current Cadence'!K39 -> FY 27 Q2 | I44: ='Current Cadence'!L39 -> No | J44: ='Current Cadence'!M39 -> Upside Deal | K44: ='Current Cadence'!N39 -> Medium | L44: ='Current Cadence'!O39 -> 0 | M44: ='Current Cadence'!P39 -> Sean Royds | ... U44: ='Current Cadence'!X39 -> 0
A45: ='Current Cadence'!#REF! -> #REF! | B45: ='Current Cadence'!#REF! -> #REF! | C45: ='Current Cadence'!#REF! -> #REF! | D45: ='Current Cadence'!#REF! -> #REF! | E45: ='Current Cadence'!#REF! -> #REF! | F45: ='Current Cadence'!#REF! -> #REF! | G45: ='Current Cadence'!#REF! -> #REF! | H45: ='Current Cadence'!#REF! -> #REF! | ... U45: ='Current Cadence'!#REF! -> #REF!
A46: ='Current Cadence'!A40 -> ITSS Cisco LoB | B46: ='Current Cadence'!B40 -> Sanlam Life Insurance Limited | C46: ='Current Cadence'!C40 -> FSI & Retail | D46: ='Current Cadence'!D40 -> OPP145901 | E46: ='Current Cadence'!E40 -> 4249038.3 | F46: ='Current Cadence'!I40 -> Commit | G46: ='Current Cadence'!J40 -> 46327 | H46: ='Current Cadence'!K40 -> FY 27 Q3 | I46: ='Current Cadence'!L40 -> No | J46: ='Current Cadence'!M40 -> Backlog Deal | K46: ='Current Cadence'!N40 -> High | L46: ='Current Cadence'!O40 -> 0 | M46: ='Current Cadence'!P40 -> Sean Royds | ... U46: ='Current Cadence'!X40 -> 0
A47: ='Current Cadence'!A41 -> ITSS Cisco LoB | B47: ='Current Cadence'!B41 -> AVI Financial Services (Pty) Ltd | C47: ='Current Cadence'!C41 -> Corporate | D47: ='Current Cadence'!D41 -> OPP125425/13 | E47: ='Current Cadence'!E41 -> 4181579.7 | F47: ='Current Cadence'!I41 -> Upside | G47: ='Current Cadence'!J41 -> 46296 | H47: ='Current Cadence'!K41 -> FY 27 Q3 | I47: ='Current Cadence'!L41 -> No | J47: ='Current Cadence'!M41 -> Upside Deal | K47: ='Current Cadence'!N41 -> High | L47: ='Current Cadence'!O41 -> checked | M47: ='Current Cadence'!P41 -> Lawrence Lethuba | ... U47: ='Current Cadence'!X41 -> 0
A48: ='Current Cadence'!A42 -> ITSS Cisco LoB | B48: ='Current Cadence'!B42 -> Sasol South Africa Limited | C48: ='Current Cadence'!C42 -> Mining Indust&Health | D48: ='Current Cadence'!D42 -> OPP147303 | E48: ='Current Cadence'!E42 -> 4120766.5 | F48: ='Current Cadence'!I42 -> Commit | G48: ='Current Cadence'!J42 -> 46174 | H48: ='Current Cadence'!K42 -> FY 27 Q1 | I48: ='Current Cadence'!L42 -> No | J48: ='Current Cadence'!M42 -> Backlog Deal | K48: ='Current Cadence'!N42 -> High | L48: ='Current Cadence'!O42 -> Checked | M48: ='Current Cadence'!P42 -> Nowell Duze | ... U48: ='Current Cadence'!X42 -> 0
A49: ='Current Cadence'!A43 -> ITSS Cisco LoB | B49: ='Current Cadence'!B43 -> Sanlam Life Insurance Limited | C49: ='Current Cadence'!C43 -> FSI & Retail | D49: ='Current Cadence'!D43 -> OPP145900 | E49: ='Current Cadence'!E43 -> 4059485.9 | F49: ='Current Cadence'!I43 -> Commit | G49: ='Current Cadence'!J43 -> 46235 | H49: ='Current Cadence'!K43 -> FY 27 Q2 | I49: ='Current Cadence'!L43 -> No | J49: ='Current Cadence'!M43 -> Backlog Deal | K49: ='Current Cadence'!N43 -> High | L49: ='Current Cadence'!O43 -> 0 | M49: ='Current Cadence'!P43 -> Sean Royds | ... U49: ='Current Cadence'!X43 -> 0
A50: ='Current Cadence'!A44 -> ITSS Cisco LoB | B50: ='Current Cadence'!B44 -> Sasol South Africa Limited | C50: ='Current Cadence'!C44 -> Mining Indust&Health | D50: ='Current Cadence'!D44 -> OPP146361 | E50: ='Current Cadence'!E44 -> 4057210.5 | F50: ='Current Cadence'!I44 -> Commit | G50: ='Current Cadence'!J44 -> 46204 | H50: ='Current Cadence'!K44 -> FY 27 Q2 | I50: ='Current Cadence'!L44 -> No | J50: ='Current Cadence'!M44 -> Backlog Deal | K50: ='Current Cadence'!N44 -> High | L50: ='Current Cadence'!O44 -> Checked | M50: ='Current Cadence'!P44 -> Nowell Duze | ... U50: ='Current Cadence'!X44 -> 0
A51: ='Current Cadence'!#REF! -> #REF! | B51: ='Current Cadence'!#REF! -> #REF! | C51: ='Current Cadence'!#REF! -> #REF! | D51: ='Current Cadence'!#REF! -> #REF! | E51: ='Current Cadence'!#REF! -> #REF! | F51: ='Current Cadence'!#REF! -> #REF! | G51: ='Current Cadence'!#REF! -> #REF! | H51: ='Current Cadence'!#REF! -> #REF! | ... U51: ='Current Cadence'!#REF! -> #REF!
A52: ='Current Cadence'!#REF! -> #REF! | B52: ='Current Cadence'!#REF! -> #REF! | C52: ='Current Cadence'!#REF! -> #REF! | D52: ='Current Cadence'!#REF! -> #REF! | E52: ='Current Cadence'!#REF! -> #REF! | F52: ='Current Cadence'!#REF! -> #REF! | G52: ='Current Cadence'!#REF! -> #REF! | H52: ='Current Cadence'!#REF! -> #REF! | ... U52: ='Current Cadence'!#REF! -> #REF!
A53: ='Current Cadence'!A45 -> ITSS Cisco LoB | B53: ='Current Cadence'!B45 -> Sanlam Life Insurance Limited | C53: ='Current Cadence'!C45 -> FSI & Retail | D53: ='Current Cadence'!D45 -> OPP146115 | E53: ='Current Cadence'!E45 -> 3926119.1 | F53: ='Current Cadence'!I45 -> Upside | G53: ='Current Cadence'!J45 -> 46235 | H53: ='Current Cadence'!K45 -> FY 27 Q2 | I53: ='Current Cadence'!L45 -> No | J53: ='Current Cadence'!M45 -> Upside Deal | K53: ='Current Cadence'!N45 -> Medium | L53: ='Current Cadence'!O45 -> 0 | M53: ='Current Cadence'!P45 -> Sean Royds | ... U53: ='Current Cadence'!X45 -> 0
A54: ='Current Cadence'!A46 -> ITSS Cisco LoB | B54: ='Current Cadence'!B46 -> Nedbank Limited | C54: ='Current Cadence'!C46 -> FSI & Retail | D54: ='Current Cadence'!D46 -> OPP146264 | E54: ='Current Cadence'!E46 -> 3303945 | F54: ='Current Cadence'!I46 -> Commit | G54: ='Current Cadence'!J46 -> 46143 | H54: ='Current Cadence'!K46 -> FY 27 Q1 | I54: ='Current Cadence'!L46 -> No | J54: ='Current Cadence'!M46 -> Backlog Deal | K54: ='Current Cadence'!N46 -> High | L54: ='Current Cadence'!O46 -> Checked | M54: ='Current Cadence'!P46 -> Sean Royds | ... U54: ='Current Cadence'!X46 -> 0
A55: ='Current Cadence'!A47 -> ITSS Cisco LoB | B55: ='Current Cadence'!B47 -> Woolworths (Pty) Limited | C55: ='Current Cadence'!C47 -> FSI & Retail | D55: ='Current Cadence'!D47 -> OPP125614 | E55: ='Current Cadence'!E47 -> 3549755 | F55: ='Current Cadence'!I47 -> Commit | G55: ='Current Cadence'!J47 -> 46174 | H55: ='Current Cadence'!K47 -> FY 27 Q1 | I55: ='Current Cadence'!L47 -> No | J55: ='Current Cadence'!M47 -> Backlog Deal | K55: ='Current Cadence'!N47 -> High | L55: ='Current Cadence'!O47 -> 0 | M55: ='Current Cadence'!P47 -> Olden Pieterse | ... U55: ='Current Cadence'!X47 -> 0
A56: ='Current Cadence'!A48 -> ITSS Cisco LoB | B56: ='Current Cadence'!B48 -> AVI Financial Services (Pty) Ltd | C56: ='Current Cadence'!C48 -> Corporate | D56: ='Current Cadence'!D48 -> OPP132983 | E56: ='Current Cadence'!E48 -> 3498223.4 | F56: ='Current Cadence'!I48 -> Upside | G56: ='Current Cadence'!J48 -> 46266 | H56: ='Current Cadence'!K48 -> FY 27 Q2 | I56: ='Current Cadence'!L48 -> No | J56: ='Current Cadence'!M48 -> Upside Deal | K56: ='Current Cadence'!N48 -> High | L56: ='Current Cadence'!O48 -> checked | M56: ='Current Cadence'!P48 -> Lawrence Lethuba | ... U56: ='Current Cadence'!X48 -> 0
A57: ='Current Cadence'!A49 -> ITSS Cisco LoB | B57: ='Current Cadence'!B49 -> AVI Financial Services (Pty) Ltd | C57: ='Current Cadence'!C49 -> Corporate | D57: ='Current Cadence'!D49 -> OPP125425/14 | E57: ='Current Cadence'!E49 -> 3341660.3 | F57: ='Current Cadence'!I49 -> Upside | G57: ='Current Cadence'!J49 -> 46266 | H57: ='Current Cadence'!K49 -> FY 27 Q2 | I57: ='Current Cadence'!L49 -> No | J57: ='Current Cadence'!M49 -> Upside Deal | K57: ='Current Cadence'!N49 -> Medium | L57: ='Current Cadence'!O49 -> checked | M57: ='Current Cadence'!P49 -> Lawrence Lethuba | ... U57: ='Current Cadence'!X49 -> 0
A58: ='Current Cadence'!A50 -> ITSS Cisco LoB | B58: ='Current Cadence'!B50 -> FNZ Software Solutions | C58: ='Current Cadence'!C50 -> Corporate | D58: ='Current Cadence'!D50 -> OPP146221 | E58: ='Current Cadence'!E50 -> 3158297 | F58: ='Current Cadence'!I50 -> Upside | G58: ='Current Cadence'!J50 -> 46296 | H58: ='Current Cadence'!K50 -> FY 27 Q3 | I58: ='Current Cadence'!L50 -> No | J58: ='Current Cadence'!M50 -> Upside Deal | K58: ='Current Cadence'!N50 -> Medium | L58: ='Current Cadence'!O50 -> Checked | M58: ='Current Cadence'!P50 -> Wandile Dlamini | ... U58: ='Current Cadence'!X50 -> 0
A59: ='Current Cadence'!A51 -> ITSS Cisco LoB | B59: ='Current Cadence'!B51 -> Sanlam Life Insurance Limited | C59: ='Current Cadence'!C51 -> FSI & Retail | D59: ='Current Cadence'!D51 -> OPP146954 | E59: ='Current Cadence'!E51 -> 3127270.3 | F59: ='Current Cadence'!I51 -> Upside | G59: ='Current Cadence'!J51 -> 46266 | H59: ='Current Cadence'!K51 -> FY 27 Q2 | I59: ='Current Cadence'!L51 -> No | J59: ='Current Cadence'!M51 -> Upside Deal | K59: ='Current Cadence'!N51 -> High | L59: ='Current Cadence'!O51 -> 0 | M59: ='Current Cadence'!P51 -> Sean Royds | ... U59: ='Current Cadence'!X51 -> 0
A60: ='Current Cadence'!A52 -> ITSS Cisco LoB | B60: ='Current Cadence'!B52 -> Run Rate | C60: ='Current Cadence'!C52 -> SAP Backlog / Invoiced | D60: ='Current Cadence'!D52 -> TBC | E60: ='Current Cadence'!E52 -> 3115500.8 | F60: ='Current Cadence'!I52 -> Upside | G60: ='Current Cadence'!J52 -> 46174 | H60: ='Current Cadence'!K52 -> FY 27 Q1 | I60: ='Current Cadence'!L52 -> No | J60: ='Current Cadence'!M52 -> Upside Deal | K60: ='Current Cadence'!N52 -> High | L60: ='Current Cadence'!O52 -> 0 | M60: ='Current Cadence'!P52 -> 0 | ... U60: ='Current Cadence'!X52 -> 0
A61: ='Current Cadence'!#REF! -> #REF! | B61: ='Current Cadence'!#REF! -> #REF! | C61: ='Current Cadence'!#REF! -> #REF! | D61: ='Current Cadence'!#REF! -> #REF! | E61: ='Current Cadence'!#REF! -> #REF! | F61: ='Current Cadence'!#REF! -> #REF! | G61: ='Current Cadence'!#REF! -> #REF! | H61: ='Current Cadence'!#REF! -> #REF! | ... U61: ='Current Cadence'!#REF! -> #REF!
A62: ='Current Cadence'!A53 -> ITSS Cisco LoB | B62: ='Current Cadence'!B53 -> MR PRICE | C62: ='Current Cadence'!C53 -> FSI & Retail | D62: ='Current Cadence'!D53 -> OPP147804 | E62: ='Current Cadence'!E53 -> 3083916.6 | F62: ='Current Cadence'!I53 -> Upside | G62: ='Current Cadence'!J53 -> 46204 | H62: ='Current Cadence'!K53 -> FY 27 Q2 | I62: ='Current Cadence'!L53 -> No | J62: ='Current Cadence'!M53 -> Upside Deal | K62: ='Current Cadence'!N53 -> Low | L62: ='Current Cadence'!O53 -> 0 | M62: ='Current Cadence'!P53 -> Olden Pieterse | ... U62: ='Current Cadence'!X53 -> 0
A63: ='Current Cadence'!A54 -> ITSS Cisco LoB | B63: ='Current Cadence'!B54 -> AVI Financial Services (Pty) Ltd | C63: ='Current Cadence'!C54 -> Corporate | D63: ='Current Cadence'!D54 -> OPP125425/08 | E63: ='Current Cadence'!E54 -> 3066160 | F63: ='Current Cadence'!I54 -> Upside | G63: ='Current Cadence'!J54 -> 46266 | H63: ='Current Cadence'!K54 -> FY 27 Q2 | I63: ='Current Cadence'!L54 -> No | J63: ='Current Cadence'!M54 -> Upside Deal | K63: ='Current Cadence'!N54 -> High | L63: ='Current Cadence'!O54 -> checked | M63: ='Current Cadence'!P54 -> Lawrence Lethuba | ... U63: ='Current Cadence'!X54 -> 0
A64: ='Current Cadence'!A55 -> ITSS Cisco LoB | B64: ='Current Cadence'!B55 -> Old Mutual Insure | C64: ='Current Cadence'!C55 -> FSI & Retail | D64: ='Current Cadence'!D55 -> OPP144877 | E64: ='Current Cadence'!E55 -> 3000000 | F64: ='Current Cadence'!I55 -> Upside | G64: ='Current Cadence'!J55 -> 46296 | H64: ='Current Cadence'!K55 -> FY 27 Q3 | I64: ='Current Cadence'!L55 -> No | J64: ='Current Cadence'!M55 -> Upside Deal | K64: ='Current Cadence'!N55 -> Medium | L64: ='Current Cadence'!O55 -> 0 | M64: ='Current Cadence'!P55 -> Sean Royds | ... U64: ='Current Cadence'!X55 -> 0
A65: ='Current Cadence'!A56 -> ITSS Cisco LoB | B65: ='Current Cadence'!B56 -> Nedbank Limited | C65: ='Current Cadence'!C56 -> FSI & Retail | D65: ='Current Cadence'!D56 -> OPP146356 | E65: ='Current Cadence'!E56 -> 2929292.9 | F65: ='Current Cadence'!I56 -> Upside | G65: ='Current Cadence'!J56 -> 46419 | H65: ='Current Cadence'!K56 -> FY 27 Q4 | I65: ='Current Cadence'!L56 -> No | J65: ='Current Cadence'!M56 -> Upside Deal | K65: ='Current Cadence'!N56 -> High | L65: ='Current Cadence'!O56 -> 0 | M65: ='Current Cadence'!P56 -> Sean Royds | ... U65: ='Current Cadence'!X56 -> 0
A66: ='Current Cadence'!A57 -> ITSS Cisco LoB | B66: ='Current Cadence'!B57 -> Ethekwini Municipality | C66: ='Current Cadence'!C57 -> Public | D66: ='Current Cadence'!D57 -> OPP146897 | E66: ='Current Cadence'!E57 -> 2855832 | F66: ='Current Cadence'!I57 -> Upside | G66: ='Current Cadence'!J57 -> 46235 | H66: ='Current Cadence'!K57 -> FY 27 Q2 | I66: ='Current Cadence'!L57 -> No | J66: ='Current Cadence'!M57 -> Upside Deal | K66: ='Current Cadence'!N57 -> Low | L66: ='Current Cadence'!O57 -> Checked | M66: ='Current Cadence'!P57 -> Wandile Dlamini | ... U66: ='Current Cadence'!X57 -> 0
A67: ='Current Cadence'!A58 -> ITSS Cisco LoB | B67: ='Current Cadence'!B58 -> Investec Bank Limited | C67: ='Current Cadence'!C58 -> FSI & Retail | D67: ='Current Cadence'!D58 -> OPP139009 | E67: ='Current Cadence'!E58 -> 2849544.4 | F67: ='Current Cadence'!I58 -> Upside | G67: ='Current Cadence'!J58 -> 46235 | H67: ='Current Cadence'!K58 -> FY 27 Q2 | I67: ='Current Cadence'!L58 -> No | J67: ='Current Cadence'!M58 -> Upside Deal | K67: ='Current Cadence'!N58 -> Low | L67: ='Current Cadence'!O58 -> 0 | M67: ='Current Cadence'!P58 -> Sean Royds | ... U67: ='Current Cadence'!X58 -> 0
A68: ='Current Cadence'!A59 -> ITSS Cisco LoB | B68: ='Current Cadence'!B59 -> Cape Peninsula University of Techno | C68: ='Current Cadence'!C59 -> Public | D68: ='Current Cadence'!D59 -> OPP146451 | E68: ='Current Cadence'!E59 -> 2750816.6 | F68: ='Current Cadence'!I59 -> Commit | G68: ='Current Cadence'!J59 -> 46235 | H68: ='Current Cadence'!K59 -> FY 27 Q2 | I68: ='Current Cadence'!L59 -> No | J68: ='Current Cadence'!M59 -> Backlog Deal | K68: ='Current Cadence'!N59 -> High | L68: ='Current Cadence'!O59 -> 0 | M68: ='Current Cadence'!P59 -> Olden Pieterse | ... U68: ='Current Cadence'!X59 -> 0
A69: ='Current Cadence'!A60 -> ITSS Cisco LoB | B69: ='Current Cadence'!B60 -> Mossel Bay Municipality | C69: ='Current Cadence'!C60 -> Public | D69: ='Current Cadence'!D60 -> OPP145648 | E69: ='Current Cadence'!E60 -> 2725320 | F69: ='Current Cadence'!I60 -> Upside | G69: ='Current Cadence'!J60 -> 46266 | H69: ='Current Cadence'!K60 -> FY 27 Q2 | I69: ='Current Cadence'!L60 -> No | J69: ='Current Cadence'!M60 -> Upside Deal | K69: ='Current Cadence'!N60 -> Low | L69: ='Current Cadence'!O60 -> Checked | M69: ='Current Cadence'!P60 -> Wandile Dlamini | ... U69: ='Current Cadence'!X60 -> 0
A70: ='Current Cadence'!A61 -> ITSS Cisco LoB | B70: ='Current Cadence'!B61 -> Sanlam Life Insurance Limited | C70: ='Current Cadence'!C61 -> FSI & Retail | D70: ='Current Cadence'!D61 -> OPP146567 | E70: ='Current Cadence'!E61 -> 2723042.2 | F70: ='Current Cadence'!I61 -> Upside | G70: ='Current Cadence'!J61 -> 46204 | H70: ='Current Cadence'!K61 -> FY 27 Q2 | I70: ='Current Cadence'!L61 -> No | J70: ='Current Cadence'!M61 -> Upside Deal | K70: ='Current Cadence'!N61 -> Medium | L70: ='Current Cadence'!O61 -> 0 | M70: ='Current Cadence'!P61 -> Sean Royds | ... U70: ='Current Cadence'!X61 -> 0
A71: ='Current Cadence'!A62 -> ITSS Cisco LoB | B71: ='Current Cadence'!B62 -> RCL Consumer - Randfontein | C71: ='Current Cadence'!C62 -> Corporate | D71: ='Current Cadence'!D62 -> OPP146935 | E71: ='Current Cadence'!E62 -> 2718159.6 | F71: ='Current Cadence'!I62 -> Upside | G71: ='Current Cadence'!J62 -> 46327 | H71: ='Current Cadence'!K62 -> FY 27 Q3 | I71: ='Current Cadence'!L62 -> No | J71: ='Current Cadence'!M62 -> Upside Deal | K71: ='Current Cadence'!N62 -> High | L71: ='Current Cadence'!O62 -> Checked | M71: ='Current Cadence'!P62 -> Hein Botha | ... U71: ='Current Cadence'!X62 -> 0
A72: ='Current Cadence'!A63 -> ITSS Cisco LoB | B72: ='Current Cadence'!B63 -> Openserve (Pty) Ltd | C72: ='Current Cadence'!C63 -> Mining Indust&Health | D72: ='Current Cadence'!D63 -> OPP131296 | E72: ='Current Cadence'!E63 -> 2708682 | F72: ='Current Cadence'!I63 -> Commit | G72: ='Current Cadence'!J63 -> 46174 | H72: ='Current Cadence'!K63 -> FY 27 Q1 | I72: ='Current Cadence'!L63 -> No | J72: ='Current Cadence'!M63 -> Backlog Deal | K72: ='Current Cadence'!N63 -> High | L72: ='Current Cadence'!O63 -> checked | M72: ='Current Cadence'!P63 -> Johan Taljaard | ... U72: ='Current Cadence'!X63 -> 0
A73: ='Current Cadence'!A64 -> ITSS Cisco LoB | B73: ='Current Cadence'!B64 -> Nelson Mandela Children's Hospital | C73: ='Current Cadence'!C64 -> Public | D73: ='Current Cadence'!D64 -> OPP148147 | E73: ='Current Cadence'!E64 -> 2703682.7 | F73: ='Current Cadence'!I64 -> Upside | G73: ='Current Cadence'!J64 -> 46266 | H73: ='Current Cadence'!K64 -> FY 27 Q2 | I73: ='Current Cadence'!L64 -> No | J73: ='Current Cadence'!M64 -> Upside Deal | K73: ='Current Cadence'!N64 -> Low | L73: ='Current Cadence'!O64 -> Checked | M73: ='Current Cadence'!P64 -> Wandile Dlamini | ... U73: ='Current Cadence'!X64 -> 0
A74: ='Current Cadence'!A65 -> ITSS Cisco LoB | B74: ='Current Cadence'!B65 -> AVI Financial Services (Pty) Ltd | C74: ='Current Cadence'!C65 -> Corporate | D74: ='Current Cadence'!D65 -> OPP137317 | E74: ='Current Cadence'!E65 -> 2701274.2 | F74: ='Current Cadence'!I65 -> Upside | G74: ='Current Cadence'!J65 -> 46266 | H74: ='Current Cadence'!K65 -> FY 27 Q2 | I74: ='Current Cadence'!L65 -> No | J74: ='Current Cadence'!M65 -> Upside Deal | K74: ='Current Cadence'!N65 -> High | L74: ='Current Cadence'!O65 -> checked | M74: ='Current Cadence'!P65 -> Lawrence Lethuba | ... U74: ='Current Cadence'!X65 -> 0
A75: ='Current Cadence'!#REF! -> #REF! | B75: ='Current Cadence'!#REF! -> #REF! | C75: ='Current Cadence'!#REF! -> #REF! | D75: ='Current Cadence'!#REF! -> #REF! | E75: ='Current Cadence'!#REF! -> #REF! | F75: ='Current Cadence'!#REF! -> #REF! | G75: ='Current Cadence'!#REF! -> #REF! | H75: ='Current Cadence'!#REF! -> #REF! | ... U75: ='Current Cadence'!#REF! -> #REF!
A76: ='Current Cadence'!A66 -> ITSS Cisco LoB | B76: ='Current Cadence'!B66 -> The Spar Group Ltd | C76: ='Current Cadence'!C66 -> FSI & Retail | D76: ='Current Cadence'!D66 -> OPP147253 | E76: ='Current Cadence'!E66 -> 2665953 | F76: ='Current Cadence'!I66 -> Commit | G76: ='Current Cadence'!J66 -> 46235 | H76: ='Current Cadence'!K66 -> FY 27 Q2 | I76: ='Current Cadence'!L66 -> No | J76: ='Current Cadence'!M66 -> Backlog Deal | K76: ='Current Cadence'!N66 -> High | L76: ='Current Cadence'!O66 -> 0 | M76: ='Current Cadence'!P66 -> Olden Pieterse | ... U76: ='Current Cadence'!X66 -> 0
A77: ='Current Cadence'!#REF! -> #REF! | B77: ='Current Cadence'!#REF! -> #REF! | C77: ='Current Cadence'!#REF! -> #REF! | D77: ='Current Cadence'!#REF! -> #REF! | E77: ='Current Cadence'!#REF! -> #REF! | F77: ='Current Cadence'!#REF! -> #REF! | G77: ='Current Cadence'!#REF! -> #REF! | H77: ='Current Cadence'!#REF! -> #REF! | ... U77: ='Current Cadence'!#REF! -> #REF!
A78: ='Current Cadence'!A67 -> ITSS Cisco LoB | B78: ='Current Cadence'!B67 -> South32 - Hillside Aluminium | C78: ='Current Cadence'!C67 -> Mining Indust&Health | D78: ='Current Cadence'!D67 -> OPP141257 | E78: ='Current Cadence'!E67 -> 2586450.1 | F78: ='Current Cadence'!I67 -> Upside | G78: ='Current Cadence'!J67 -> 46327 | H78: ='Current Cadence'!K67 -> FY 27 Q3 | I78: ='Current Cadence'!L67 -> No | J78: ='Current Cadence'!M67 -> Upside Deal | K78: ='Current Cadence'!N67 -> Medium | L78: ='Current Cadence'!O67 -> Checked | M78: ='Current Cadence'!P67 -> Hein Botha | ... U78: ='Current Cadence'!X67 -> 0
A79: ='Current Cadence'!A68 -> ITSS Cisco LoB | B79: ='Current Cadence'!B68 -> TFG | C79: ='Current Cadence'!C68 -> FSI & Retail | D79: ='Current Cadence'!D68 -> OPP147999/01 | E79: ='Current Cadence'!E68 -> 2567313.9 | F79: ='Current Cadence'!I68 -> Upside | G79: ='Current Cadence'!J68 -> 46204 | H79: ='Current Cadence'!K68 -> FY 27 Q2 | I79: ='Current Cadence'!L68 -> No | J79: ='Current Cadence'!M68 -> Upside Deal | K79: ='Current Cadence'!N68 -> Low | L79: ='Current Cadence'!O68 -> 0 | M79: ='Current Cadence'!P68 -> Olden Pieterse | ... U79: ='Current Cadence'!X68 -> 0
A80: ='Current Cadence'!#REF! -> #REF! | B80: ='Current Cadence'!#REF! -> #REF! | C80: ='Current Cadence'!#REF! -> #REF! | D80: ='Current Cadence'!#REF! -> #REF! | E80: ='Current Cadence'!#REF! -> #REF! | F80: ='Current Cadence'!#REF! -> #REF! | G80: ='Current Cadence'!#REF! -> #REF! | H80: ='Current Cadence'!#REF! -> #REF! | ... U80: ='Current Cadence'!#REF! -> #REF!
A81: ='Current Cadence'!A69 -> ITSS Cisco LoB | B81: ='Current Cadence'!B69 -> South32 - Hotazel | C81: ='Current Cadence'!C69 -> Mining Indust&Health | D81: ='Current Cadence'!D69 -> OPP148302 | E81: ='Current Cadence'!E69 -> 2499316.6 | F81: ='Current Cadence'!I69 -> Upside | G81: ='Current Cadence'!J69 -> 46235 | H81: ='Current Cadence'!K69 -> FY 27 Q2 | I81: ='Current Cadence'!L69 -> No | J81: ='Current Cadence'!M69 -> Upside Deal | K81: ='Current Cadence'!N69 -> High | L81: ='Current Cadence'!O69 -> 0 | M81: ='Current Cadence'!P69 -> Hein Botha | ... U81: ='Current Cadence'!X69 -> 0
A82: ='Current Cadence'!A70 -> ITSS Cisco LoB | B82: ='Current Cadence'!B70 -> Momentum Group-Wide Services (Pty) Ltd | C82: ='Current Cadence'!C70 -> FSI & Retail | D82: ='Current Cadence'!D70 -> OPP113848/04 | E82: ='Current Cadence'!E70 -> 2326283 | F82: ='Current Cadence'!I70 -> Commit | G82: ='Current Cadence'!J70 -> 46266 | H82: ='Current Cadence'!K70 -> FY 27 Q2 | I82: ='Current Cadence'!L70 -> No | J82: ='Current Cadence'!M70 -> Backlog Deal | K82: ='Current Cadence'!N70 -> High | L82: ='Current Cadence'!O70 -> Checked | M82: ='Current Cadence'!P70 -> Paul van Rooyen | ... U82: ='Current Cadence'!X70 -> 0
A83: ='Current Cadence'!A71 -> ITSS Cisco LoB | B83: ='Current Cadence'!B71 -> Telkom SA SOC Limited | C83: ='Current Cadence'!C71 -> Mining Indust&Health | D83: ='Current Cadence'!D71 -> OPP125388/06 | E83: ='Current Cadence'!E71 -> 2227444.7 | F83: ='Current Cadence'!I71 -> Commit | G83: ='Current Cadence'!J71 -> 46174 | H83: ='Current Cadence'!K71 -> FY 27 Q1 | I83: ='Current Cadence'!L71 -> No | J83: ='Current Cadence'!M71 -> Backlog Deal | K83: ='Current Cadence'!N71 -> High | L83: ='Current Cadence'!O71 -> checked | M83: ='Current Cadence'!P71 -> Johan Taljaard | ... U83: ='Current Cadence'!X71 -> 0
A84: ='Current Cadence'!A72 -> ITSS Cisco LoB | B84: ='Current Cadence'!B72 -> TFG | C84: ='Current Cadence'!C72 -> FSI & Retail | D84: ='Current Cadence'!D72 -> OPP147999/03 | E84: ='Current Cadence'!E72 -> 2130637.6 | F84: ='Current Cadence'!I72 -> Upside | G84: ='Current Cadence'!J72 -> 46204 | H84: ='Current Cadence'!K72 -> FY 27 Q2 | I84: ='Current Cadence'!L72 -> No | J84: ='Current Cadence'!M72 -> Upside Deal | K84: ='Current Cadence'!N72 -> Low | L84: ='Current Cadence'!O72 -> 0 | M84: ='Current Cadence'!P72 -> Olden Pieterse | ... U84: ='Current Cadence'!X72 -> 0
A85: ='Current Cadence'!A73 -> ITSS Cisco LoB | B85: ='Current Cadence'!B73 -> Woolworths (Pty) Limited | C85: ='Current Cadence'!C73 -> FSI & Retail | D85: ='Current Cadence'!D73 -> OPP101644 | E85: ='Current Cadence'!E73 -> 2128385 | F85: ='Current Cadence'!I73 -> Commit | G85: ='Current Cadence'!J73 -> 46296 | H85: ='Current Cadence'!K73 -> FY 27 Q3 | I85: ='Current Cadence'!L73 -> No | J85: ='Current Cadence'!M73 -> Backlog Deal | K85: ='Current Cadence'!N73 -> High | L85: ='Current Cadence'!O73 -> Checked | M85: ='Current Cadence'!P73 -> Olden Pieterse | ... U85: ='Current Cadence'!X73 -> 0
A86: ='Current Cadence'!A74 -> ITSS Cisco LoB | B86: ='Current Cadence'!B74 -> Openserve | C86: ='Current Cadence'!C74 -> Mining Indust&Health | D86: ='Current Cadence'!D74 -> OPP148228 | E86: ='Current Cadence'!E74 -> 2082663.5 | F86: ='Current Cadence'!I74 -> Upside | G86: ='Current Cadence'!J74 -> 46296 | H86: ='Current Cadence'!K74 -> FY 27 Q3 | I86: ='Current Cadence'!L74 -> No | J86: ='Current Cadence'!M130 -> Upside Deal | K86: ='Current Cadence'!N74 -> Medium | L86: ='Current Cadence'!O74 -> OPP148228 - Openserve WAE Renewal | M86: ='Current Cadence'!P74 -> Johan Taljaard | N86: ='Current Cadence'!Q74 -> Wimpie Pieterse | O86: ='Current Cadence'!R74 -> Software / Licence | P86: ='Current Cadence'!S74 -> 0 | Q86: ='Current Cadence'!T74 -> 0 | R86: ='Current Cadence'!U74 -> 0 | ... U86: ='Current Cadence'!X74 -> 0
A87: ='Current Cadence'!A75 -> ITSS Cisco LoB | B87: ='Current Cadence'!B75 -> Blake & Assosiates | C87: ='Current Cadence'!C75 -> Corporate | D87: ='Current Cadence'!D75 -> OPP146206 | E87: ='Current Cadence'!E75 -> 2057983 | F87: ='Current Cadence'!I75 -> Commit | G87: ='Current Cadence'!J75 -> 46235 | H87: ='Current Cadence'!K75 -> FY 27 Q2 | I87: ='Current Cadence'!L75 -> No | J87: ='Current Cadence'!M75 -> Backlog Deal | K87: ='Current Cadence'!N75 -> High | L87: ='Current Cadence'!O75 -> checked | M87: ='Current Cadence'!P75 -> Johan Taljaard | ... U87: ='Current Cadence'!X75 -> 0
A88: ='Current Cadence'!A76 -> ITSS Cisco LoB | B88: ='Current Cadence'!B76 -> Bigen Africa Group Holdings | C88: ='Current Cadence'!C76 -> Corporate | D88: ='Current Cadence'!D76 -> OPP132134 | E88: ='Current Cadence'!E76 -> 1945541.9 | F88: ='Current Cadence'!I76 -> Commit | G88: ='Current Cadence'!J76 -> 46174 | H88: ='Current Cadence'!K76 -> FY 27 Q1 | I88: ='Current Cadence'!L76 -> No | J88: ='Current Cadence'!M76 -> Backlog Deal | K88: ='Current Cadence'!N76 -> High | L88: ='Current Cadence'!O76 -> Checked | M88: ='Current Cadence'!P76 -> Wandile Dlamini | ... U88: ='Current Cadence'!X76 -> 0
A89: ='Current Cadence'!A77 -> ITSS Cisco LoB | B89: ='Current Cadence'!B77 -> Umngeni Local Municipality | C89: ='Current Cadence'!C77 -> Public | D89: ='Current Cadence'!D77 -> OPP146253 | E89: ='Current Cadence'!E77 -> 1891682 | F89: ='Current Cadence'!I77 -> Upside | G89: ='Current Cadence'!J77 -> 46296 | H89: ='Current Cadence'!K77 -> FY 27 Q3 | I89: ='Current Cadence'!L77 -> No | J89: ='Current Cadence'!M77 -> Upside Deal | K89: ='Current Cadence'!N77 -> Low | L89: ='Current Cadence'!O77 -> Checked | M89: ='Current Cadence'!P77 -> Wandile Dlamini | ... U89: ='Current Cadence'!X77 -> 0
A90: ='Current Cadence'!A78 -> ITSS Cisco LoB | B90: ='Current Cadence'!B78 -> Nedbank Limited | C90: ='Current Cadence'!C78 -> FSI & Retail | D90: ='Current Cadence'!D78 -> OPP147618 | E90: ='Current Cadence'!E78 -> 1819776 | F90: ='Current Cadence'!I78 -> Upside | G90: ='Current Cadence'!J78 -> 46327 | H90: ='Current Cadence'!K78 -> FY 27 Q3 | I90: ='Current Cadence'!L78 -> No | J90: ='Current Cadence'!M78 -> Upside Deal | K90: ='Current Cadence'!N78 -> Low | L90: ='Current Cadence'!O78 -> 0 | M90: ='Current Cadence'!P78 -> Sean Royds | ... U90: ='Current Cadence'!X78 -> 0
A91: ='Current Cadence'!A79 -> ITSS Cisco LoB | B91: ='Current Cadence'!B79 -> Openserve | C91: ='Current Cadence'!C79 -> Mining Indust&Health | D91: ='Current Cadence'!D79 -> OPP141512 | E91: ='Current Cadence'!E79 -> 1729924 | F91: ='Current Cadence'!I79 -> Upside | G91: ='Current Cadence'!J79 -> 46447 | H91: ='Current Cadence'!K79 -> FY 27 Q4 | I91: ='Current Cadence'!L79 -> No | J91: ='Current Cadence'!M79 -> Upside Deal | K91: ='Current Cadence'!N79 -> Medium | L91: ='Current Cadence'!O79 -> checked | M91: ='Current Cadence'!P79 -> Johan Taljaard | ... U91: ='Current Cadence'!X79 -> 0
A92: ='Current Cadence'!A80 -> ITSS Cisco LoB | B92: ='Current Cadence'!B80 -> Citadel Financial Services | C92: ='Current Cadence'!C80 -> Corporate | D92: ='Current Cadence'!D80 -> OPP141437 | E92: ='Current Cadence'!E80 -> 1688249.1 | F92: ='Current Cadence'!I80 -> Commit | G92: ='Current Cadence'!J80 -> 46235 | H92: ='Current Cadence'!K80 -> FY 27 Q2 | I92: ='Current Cadence'!L80 -> No | J92: ='Current Cadence'!M80 -> Backlog Deal | K92: ='Current Cadence'!N80 -> High | L92: ='Current Cadence'!O80 -> checked | M92: ='Current Cadence'!P80 -> Lawrence Lethuba | ... U92: ='Current Cadence'!X80 -> 0
A93: ='Current Cadence'!A81 -> ITSS Cisco LoB | B93: ='Current Cadence'!B81 -> TFG | C93: ='Current Cadence'!C81 -> FSI & Retail | D93: ='Current Cadence'!D81 -> OPP147999/04 | E93: ='Current Cadence'!E81 -> 1681132.8 | F93: ='Current Cadence'!I81 -> Upside | G93: ='Current Cadence'!J81 -> 46204 | H93: ='Current Cadence'!K81 -> FY 27 Q2 | I93: ='Current Cadence'!L81 -> No | J93: ='Current Cadence'!M81 -> Upside Deal | K93: ='Current Cadence'!N81 -> Low | L93: ='Current Cadence'!O81 -> 0 | M93: ='Current Cadence'!P81 -> Olden Pieterse | ... U93: ='Current Cadence'!X81 -> 0
A94: ='Current Cadence'!A82 -> ITSS Cisco LoB | B94: ='Current Cadence'!B82 -> Tiger Brands | C94: ='Current Cadence'!C82 -> FSI & Retail | D94: ='Current Cadence'!D82 -> OPP146069 | E94: ='Current Cadence'!E82 -> 1572349.9 | F94: ='Current Cadence'!I82 -> Commit | G94: ='Current Cadence'!J82 -> 46204 | H94: ='Current Cadence'!K82 -> FY 27 Q2 | I94: ='Current Cadence'!L82 -> No | J94: ='Current Cadence'!M82 -> Backlog Deal | K94: ='Current Cadence'!N82 -> High | L94: ='Current Cadence'!O82 -> Checked | M94: ='Current Cadence'!P82 -> Nowell Duze | ... U94: ='Current Cadence'!X82 -> 0
A95: ='Current Cadence'!A83 -> ITSS Cisco LoB | B95: ='Current Cadence'!B83 -> Volkswagen Group Africa (Pty) Ltd | C95: ='Current Cadence'!C83 -> Corporate | D95: ='Current Cadence'!D83 -> OPP147266 | E95: ='Current Cadence'!E83 -> 1355862 | F95: ='Current Cadence'!I83 -> Upside | G95: ='Current Cadence'!J83 -> 46235 | H95: ='Current Cadence'!K83 -> FY 27 Q2 | I95: ='Current Cadence'!L83 -> No | J95: ='Current Cadence'!M83 -> Upside Deal | K95: ='Current Cadence'!N83 -> Low | L95: ='Current Cadence'!O83 -> 0 | M95: ='Current Cadence'!P83 -> Roan van Nieuwenhuizen | ... U95: ='Current Cadence'!X83 -> 0
A96: ='Current Cadence'!A84 -> ITSS Cisco LoB | B96: ='Current Cadence'!B84 -> TFG | C96: ='Current Cadence'!C84 -> FSI & Retail | D96: ='Current Cadence'!D84 -> OPP147999/02 | E96: ='Current Cadence'!E84 -> 1343561.1 | F96: ='Current Cadence'!I84 -> Upside | G96: ='Current Cadence'!J84 -> 46204 | H96: ='Current Cadence'!K84 -> FY 27 Q2 | I96: ='Current Cadence'!L84 -> No | J96: ='Current Cadence'!M84 -> Upside Deal | K96: ='Current Cadence'!N84 -> Low | L96: ='Current Cadence'!O84 -> 0 | M96: ='Current Cadence'!P84 -> Olden Pieterse | ... U96: ='Current Cadence'!X84 -> 0
A97: ='Current Cadence'!A85 -> ITSS Cisco LoB | B97: ='Current Cadence'!B85 -> Department of Home Affairs | C97: ='Current Cadence'!C85 -> Public | D97: ='Current Cadence'!D85 -> OPP144576 | E97: ='Current Cadence'!E85 -> 1290725 | F97: ='Current Cadence'!I85 -> Commit | G97: ='Current Cadence'!J85 -> 46174 | H97: ='Current Cadence'!K85 -> FY 27 Q1 | I97: ='Current Cadence'!L85 -> No | J97: ='Current Cadence'!M85 -> Backlog Deal | K97: ='Current Cadence'!N85 -> High | L97: ='Current Cadence'!O85 -> 0 | M97: ='Current Cadence'!P85 -> David Ramorola | ... U97: ='Current Cadence'!X85 -> 0
A98: ='Current Cadence'!A86 -> ITSS Cisco LoB | B98: ='Current Cadence'!B86 -> Sanlam Life Insurance Limited | C98: ='Current Cadence'!C86 -> FSI & Retail | D98: ='Current Cadence'!D86 -> OPP145570 | E98: ='Current Cadence'!E86 -> 1289968.4 | F98: ='Current Cadence'!I86 -> Commit | G98: ='Current Cadence'!J86 -> 46174 | H98: ='Current Cadence'!K86 -> FY 27 Q1 | I98: ='Current Cadence'!L86 -> No | J98: ='Current Cadence'!M86 -> Backlog Deal | K98: ='Current Cadence'!N86 -> High | L98: ='Current Cadence'!O86 -> 0 | M98: ='Current Cadence'!P86 -> Sean Royds | ... U98: ='Current Cadence'!X86 -> 0
... A112: ='Current Cadence'!A100 -> ITSS Cisco LoB | B112: ='Current Cadence'!B100 -> Concentrix Cvg South Africa | C112: ='Current Cadence'!C100 -> Corporate | D112: ='Current Cadence'!D100 -> OPP142083 | E112: ='Current Cadence'!E100 -> 917255.58 | F112: ='Current Cadence'!I100 -> Commit | G112: ='Current Cadence'!J100 -> 46174 | H112: ='Current Cadence'!K100 -> FY 27 Q1 | I112: ='Current Cadence'!L100 -> No | J112: ='Current Cadence'!M100 -> Backlog Deal | K112: ='Current Cadence'!N100 -> High | L112: ='Current Cadence'!O100 -> 0 | M112: ='Current Cadence'!P100 -> Olden Pieterse | ... U112: ='Current Cadence'!X100 -> 0
A113: ='Current Cadence'!#REF! -> #REF! | B113: ='Current Cadence'!#REF! -> #REF! | C113: ='Current Cadence'!#REF! -> #REF! | D113: ='Current Cadence'!#REF! -> #REF! | E113: ='Current Cadence'!#REF! -> #REF! | F113: ='Current Cadence'!#REF! -> #REF! | G113: ='Current Cadence'!#REF! -> #REF! | H113: ='Current Cadence'!#REF! -> #REF! | ... U113: ='Current Cadence'!#REF! -> #REF!
A114: ='Current Cadence'!A101 -> ITSS Cisco LoB | B114: ='Current Cadence'!B101 -> Concentrix Cvg South Africa | C114: ='Current Cadence'!C101 -> Corporate | D114: ='Current Cadence'!D101 -> OPP142082 | E114: ='Current Cadence'!E101 -> 917255.58 | F114: ='Current Cadence'!I101 -> Commit | G114: ='Current Cadence'!J101 -> 46174 | H114: ='Current Cadence'!K101 -> FY 27 Q1 | I114: ='Current Cadence'!L101 -> No | J114: ='Current Cadence'!M101 -> Backlog Deal | K114: ='Current Cadence'!N101 -> High | L114: ='Current Cadence'!O101 -> 0 | M114: ='Current Cadence'!P101 -> Olden Pieterse | ... U114: ='Current Cadence'!X101 -> 0
...

Sheet DupeCheck
A1: {=_xlfn.UNIQUE('Current Cadence'!D:D)} -> 0 | B1: =COUNTIF('Current Cadence'!D:D,DupeCheck!A1) -> 0
A2: Totals | B2: =COUNTIF('Current Cadence'!D:D,DupeCheck!A2) -> 1
A3: OPP Number | B3: =COUNTIF('Current Cadence'!D:D,DupeCheck!A3) -> 1
A4: OPP145398 | B4: =COUNTIF('Current Cadence'!D:D,DupeCheck!A4) -> 1
A5: OPP146677 | B5: =COUNTIF('Current Cadence'!D:D,DupeCheck!A5) -> 1
A6: OPP136919 | B6: =COUNTIF('Current Cadence'!D:D,DupeCheck!A6) -> 1
A7: OPP133098 | B7: =COUNTIF('Current Cadence'!D:D,DupeCheck!A7) -> 1
A8: OPP147096 | B8: =COUNTIF('Current Cadence'!D:D,DupeCheck!A8) -> 1
A9: OPP147364 | B9: =COUNTIF('Current Cadence'!D:D,DupeCheck!A9) -> 1
A10: OPP145768 | B10: =COUNTIF('Current Cadence'!D:D,DupeCheck!A10) -> 1
A11: OPP147259 | B11: =COUNTIF('Current Cadence'!D:D,DupeCheck!A11) -> 1
A12: OPP13777 | B12: =COUNTIF('Current Cadence'!D:D,DupeCheck!A12) -> 1
A13: OPP135119/01 | B13: =COUNTIF('Current Cadence'!D:D,DupeCheck!A13) -> 1
... A180: OPP139075 | B180: =COUNTIF('Current Cadence'!D:D,DupeCheck!A180) -> 1
B181: =COUNTIF('Current Cadence'!D:D,DupeCheck!A181) -> 0
B182: =COUNTIF('Current Cadence'!D:D,DupeCheck!A182) -> 0
B183: =COUNTIF('Current Cadence'!D:D,DupeCheck!A183) -> 0
B184: =COUNTIF('Current Cadence'!D:D,DupeCheck!A184) -> 0
B185: =COUNTIF('Current Cadence'!D:D,DupeCheck!A185) -> 0
B186: =COUNTIF('Current Cadence'!D:D,DupeCheck!A186) -> 0
B187: =COUNTIF('Current Cadence'!D:D,DupeCheck!A187) -> 0
B188: =COUNTIF('Current Cadence'!D:D,DupeCheck!A188) -> 0
B189: =COUNTIF('Current Cadence'!D:D,DupeCheck!A189) -> 0
B190: =COUNTIF('Current Cadence'!D:D,DupeCheck!A190) -> 0
B191: =COUNTIF('Current Cadence'!D:D,DupeCheck!A191) -> 0
B192: =COUNTIF('Current Cadence'!D:D,DupeCheck!A192) -> 0
... B351: =COUNTIF('Current Cadence'!D:D,DupeCheck!A351) -> 0

Sheet ViewBeforeCopy

Sheet LiveCadenceBeforeCopy
A1: ITSS Cisco LoB | B1: Telkom Consumer | C1: Mining Indust&Health | D1: OPP133098 | E1: 33825197 | F1: 1691259.9 | G1: 1691259.9 | H1: 0.05 | I1: Commit | J1: 46174 | K1: FY 27 Q1 | L1: No | M1: Backlog Deal | N1: High | O1: checked | P1: johan Taljaard | Q1: Wimpie Pieterse | R1: OEM Service | S1: SFC Annual Payment
A2: ITSS Cisco LoB | B2: The Spar Group Ltd | C2: FSI & Retail | D2: OPP136919 | E2: 38123456 | F2: 4574814.7 | G2: 4574814.7 | H2: 0.12 | I2: Upside | J2: 46174 | K2: FY 27 Q1 | L2: No | M2: Upside Deal | N2: High | O2: checked | P2: Roan van Nieuwenhuizen | Q2: Wimpie Pieterse | R2: Software / Licence | S2: Need to move Licenses to another ORG to reduce the License limit. This is before we can create Cisco Meraki EA
A3: ITSS Cisco LoB | B3: Telkom Consumer | C3: Mining Indust&Health | D3: OPP147259 | E3: 21938052 | F3: 21938052 | G3: 2193805.2 | H3: 0.1 | I3: Upside | J3: 46327 | K3: FY 27 Q3 | L3: No | M3: Upside Deal | N3: Low | O3: checked | P3: Johan Taljaard | Q3: Wimpie Pieterse | R3: Product
A4: ITSS Cisco LoB | B4: Telkom Consumer | C4: Mining Indust&Health | D4: OPP135119/01 | E4: 15799289 | F4: 15799289 | G4: 1421936 | H4: 0.09 | I4: Upside | J4: 46327 | K4: FY 27 Q3 | L4: No | M4: Upside Deal | N4: Medium | O4: checked | P4: Johan Taljaard | Q4: Wimpie Pieterse | R4: Product | S4: EDD 154 days after order placement - Nutanix Expansion Value updated, Busy repricing will be resubmitted to Telkom
A5: ITSS Cisco LoB | B5: Openserve (Pty) Ltd | C5: Mining Indust&Health | D5: OPP145588 | E5: 13312345 | F5: 665617.25 | G5: 665617.25 | H5: 0.05 | I5: Upside | J5: 46174 | K5: FY 27 Q1 | L5: No | M5: Upside Deal | N5: High | O5: checked | P5: Johan Taljaard | Q5: Wimpie Pieterse | R5: OEM Service | S5: Opernserve Sweep Year 1 of 3
A6: ITSS Cisco LoB | B6: Discovery Central Services (Pty) Ltd | C6: FSI & Retail | D6: OPP147096 | E6: 30614619 | F6: 30614619 | G6: 1530730.9 | H6: 0.05 | I6: Upside | J6: 46235 | K6: FY 27 Q2 | L6: No | M6: Upside Deal | N6: Low | O6: checked | P6: Paul van Rooyen | Q6: Wimpie Pieterse | R6: Product | S6: RFQ - Network refresh
A7: ITSS Cisco LoB | B7: Nedbank Limited | C7: FSI & Retail | D7: OPP147252 | E7: 14378595 | F7: 862715.69 | G7: 862715.69 | H7: 0.06 | I7: Upside | J7: 46266 | K7: FY 27 Q2 | L7: No | M7: Upside Deal | N7: Low | O7: Checked | P7: Sean Royds | Q7: Wimpie Pieterse | R7: Product | S7: Budgetsry for Jac-Lou Wireless Guest Portal Business Case
A8: ITSS Cisco LoB | B8: Nedbank Limited | C8: FSI & Retail | D8: OPP147043 | E8: 5790700.2 | F8: 5790700.2 | G8: 347442.01 | H8: 0.06 | I8: Commit | J8: 46204 | K8: FY 27 Q2 | L8: No | M8: Backlog Deal | N8: High | P8: Sean Royds | Q8: Wimpie Pieterse | R8: Product | S8: EDD 16 July; Shuaib will push to add to NBV Jul signoff
A9: ITSS Cisco LoB | B9: Momentum Metropolitan Life Ltd Metropolitan | C9: FSI & Retail | D9: OPP142558 | E9: 5238762.6 | F9: 5238762.6 | G9: 628651.51 | H9: 0.12 | I9: Commit | J9: 46143 | K9: FY 27 Q1 | L9: Yes | M9: Backlog Deal | N9: High | O9: Checked | P9: Wandile Dlamini | Q9: Wimpie Pieterse | R9: Product | S9: EDD 196 days after order placement - New Rivonia branch
A10: ITSS Cisco LoB | B10: Sanlam Life Insurance Limited | C10: FSI & Retail | D10: OPP145900 | E10: 4059485.9 | F10: 4059485.9 | G10: 405948.59 | H10: 0.1 | I10: Commit | J10: 46235 | K10: FY 27 Q2 | L10: No | M10: Backlog Deal | N10: High | P10: Sean Royds | Q10: Wimpie Pieterse | R10: Product | S10: EDD 29 July 2026
A11: ITSS Cisco LoB | B11: Nedbank Limited | C11: FSI & Retail | D11: OPP146264 | E11: 3776766.7 | F11: 3776766.7 | G11: 226606 | H11: 0.06 | I11: Commit | J11: 46174 | K11: FY 27 Q1 | L11: No | M11: Backlog Deal | N11: High | P11: Sean Royds | Q11: Wimpie Pieterse | R11: Product | S11: Partial Invoice Chassis in May, Awaiting SFP's due Jun (EDD 29 May 2026)
A12: ITSS Cisco LoB | B12: Woolworths (Pty) Limited | C12: FSI & Retail | D12: OPP125614 | E12: 3549755 | F12: 3532442.3 | G12: 353244.23 | H12: 0.1 | I12: Commit | J12: 46174 | K12: FY 27 Q1 | L12: No | M12: Backlog Deal | N12: High | P12: Olden Pieterse | Q12: Wimpie Pieterse | R12: Product | S12: EDD 196 days from order - DC3 refresh
A13: ITSS Cisco LoB | B13: The Spar Group Ltd | C13: FSI & Retail | D13: OPP147253 | E13: 2665953 | F13: 2665953 | G13: 319914.36 | H13: 0.12 | I13: Commit | J13: 46235 | K13: FY 27 Q2 | L13: No | M13: Backlog Deal | N13: High | P13: Olden Pieterse | Q13: Wimpie Pieterse | R13: Product | S13: EDD 18 June - VC equipment
A14: ITSS Cisco LoB | B14: Sanlam Life Insurance Limited | C14: FSI & Retail | D14: OPP145570 | E14: 1289968.4 | F14: 1289968.4 | G14: 128996.84 | H14: 0.1 | I14: Commit | J14: 46174 | K14: FY 27 Q1 | L14: No | M14: Backlog Deal | N14: High | P14: Sean Royds | Q14: Wimpie Pieterse | R14: Product | S14: EDD 3 June 2026 - Additional Line Card modules
A15: ITSS Cisco LoB | B15: Pioneer Foods (Pty) Ltd | C15: FSI & Retail | D15: OPP131208/04 | E15: 1104339 | F15: 1104339 | G15: 110433.9 | H15: 0.1 | I15: Commit | J15: 46388 | K15: FY 27 Q4 | L15: No | M15: Backlog Deal | N15: High | P15: Olden Pieterse | Q15: Wimpie Pieterse | R15: Product | S15: EDD May - Aeroton Bakery - order received
A16: ITSS Cisco LoB | B16: Momentum Group-Wide Services (Pty) Ltd | C16: FSI & Retail | D16: OPP113848/04 | E16: 2326283 | F16: 232628.3 | G16: 232628.3 | H16: 0.1 | I16: Commit | J16: 46266 | K16: FY 27 Q2 | L16: No | M16: Backlog Deal | N16: High | O16: Checked | P16: Paul van Rooyen | Q16: Wimpie Pieterse | R16: Software / Licence | S16: Stanlib APP-D year 2/3
A17: ITSS Cisco LoB | B17: The Spar Group Ltd | C17: FSI & Retail | D17: OPP147073 | E17: 1056330 | F17: 1056330 | G17: 126759.6 | H17: 0.12 | I17: Commit | J17: 46143 | K17: FY 27 Q1 | L17: Yes | M17: Backlog Deal | N17: High | P17: Olden Pieterse | Q17: Wimpie Pieterse | R17: Product | S17: EDD 4 May - 200 x MX67
A18: ITSS Cisco LoB | B18: Tiger Consumer Brands Limited | C18: FSI & Retail | D18: OPP146069 | E18: 1572349.9 | F18: 1572349.9 | G18: 125787.99 | H18: 0.08 | I18: Commit | J18: 46204 | K18: FY 27 Q2 | L18: No | M18: Backlog Deal | N18: High | P18: Nowell Duze | Q18: Wimpie Pieterse | R18: Product
A19: ITSS Cisco LoB | B19: Tiger Consumer Brands Limited | C19: FSI & Retail | D19: OPP138466 | E19: 10753040 | F19: 860243.23 | G19: 860243.23 | H19: 0.08 | I19: Upside | J19: 46204 | K19: FY 27 Q2 | L19: No | M19: Upside Deal | N19: Low | P19: Nowell Duze | Q19: Wimpie Pieterse | R19: Product | S19: Quote refreshed on the 18th of May. Vblock DC switches
A20: ITSS Cisco LoB | B20: Tiger Consumer Brands Limited | C20: FSI & Retail | D20: OPP146660 | E20: 5301769.3 | F20: 5301769.3 | G20: 424141.55 | H20: 0.08 | I20: Upside | J20: 46204 | K20: FY 27 Q2 | L20: No | M20: Upside Deal | N20: Low | P20: Nowell Duze | Q20: Wimpie Pieterse | R20: Product | S20: Bafo Pricing submitted on the 22nd May 2026
A21: ITSS Cisco LoB | B21: Sanlam Life Insurance Limited | C21: FSI & Retail | D21: OPP137867 | E21: 4963898 | F21: 4963898 | G21: 496389.8 | H21: 0.1 | I21: Upside | J21: 46235 | K21: FY 27 Q2 | L21: No | M21: Upside Deal | N21: Medium | P21: Sean Royds | Q21: Wimpie Pieterse | R21: Product | S21: EDD 56 days after order placement - Assupol SD-WAN Routers
A22: ITSS Cisco LoB | B22: Pioneer Foods (Pty) Ltd | C22: FSI & Retail | D22: OPP136579/03 | E22: 655608 | F22: 655608 | G22: 65560.8 | H22: 0.1 | I22: Commit | J22: 46388 | K22: FY 27 Q4 | L22: No | M22: Backlog Deal | N22: High | P22: Olden Pieterse | Q22: Wimpie Pieterse | R22: Product | S22: EDD May - SAD Upington - order received
A23: ITSS Cisco LoB | B23: Sanlam | C23: FSI & Retail | D23: OPP146115 | E23: 3926119.1 | F23: 3926119.1 | G23: 392611.91 | H23: 0.1 | I23: Upside | J23: 46235 | K23: FY 27 Q2 | L23: No | M23: Upside Deal | N23: Medium | O23: Checked | P23: Sean Royds | Q23: Wimpie Pieterse | R23: Product | S23: Sanlam reviewing to potentially bundle deals together
A24: ITSS Cisco LoB | B24: MR PRICE | C24: FSI & Retail | D24: OPP147804 | E24: 3083916.6 | F24: 308391.66 | G24: 308391.66 | H24: 0.1 | I24: Upside | J24: 46204 | K24: FY 27 Q2 | L24: No | M24: Upside Deal | N24: Low | P24: Olden Pieterse | Q24: Wimpie Pieterse | R24: Product | S24: Submitted pricing to Mr Price: Speculation at this point
A25: ITSS Cisco LoB | B25: Investec Bank Limited | C25: FSI & Retail | D25: OPP139009 | E25: 2849544.4 | F25: 2849544.4 | G25: 341945.33 | H25: 0.12 | I25: Upside | J25: 46235 | K25: FY 27 Q2 | L25: No | M25: Upside Deal | N25: Low | P25: Sean Royds | Q25: Wimpie Pieterse | R25: Product | S25: EDD 42 days after order placement - ACI hardware replacement
A26: ITSS Cisco LoB | B26: Sanlam Life Insurance Limited | C26: FSI & Retail | D26: OPP146567 | E26: 2723042.2 | F26: 2723042.2 | G26: 272304.22 | H26: 0.1 | I26: Upside | J26: 46204 | K26: FY 27 Q2 | L26: No | M26: Upside Deal | N26: Medium | O26: Checked | P26: Sean Royds | Q26: Wimpie Pieterse | R26: Product | S26: EDD 70 days from order placement - SGT 2027 EOL Replacements
A27: ITSS Cisco LoB | B27: TFG | C27: FSI & Retail | D27: OPP147999/01 | E27: 2567313.9 | F27: 128365.69 | G27: 128365.69 | H27: 0.05 | I27: Upside | J27: 46204 | K27: FY 27 Q2 | L27: No | M27: Upside Deal | N27: Low | P27: Olden Pieterse | Q27: Wimpie Pieterse | R27: Product | S27: Ndabeni Switches - Submitted Quote
A28: ITSS Cisco LoB | B28: TFG | C28: FSI & Retail | D28: OPP147999/03 | E28: 2130637.6 | F28: 106531.88 | G28: 106531.88 | H28: 0.05 | I28: Upside | J28: 46204 | K28: FY 27 Q2 | L28: No | M28: Upside Deal | N28: Low | P28: Olden Pieterse | Q28: Wimpie Pieterse | R28: Product | S28: Prestige Maitland Switches - - Submitted Quote
A29: ITSS Cisco LoB | B29: TFG | C29: FSI & Retail | D29: OPP147999/04 | E29: 1681132.8 | F29: 84056.639 | G29: 84056.639 | H29: 0.05 | I29: Upside | J29: 46204 | K29: FY 27 Q2 | L29: No | M29: Upside Deal | N29: Low | P29: Olden Pieterse | Q29: Wimpie Pieterse | R29: Product | S29: Prestige MaitlandWireless - - Submitted Quote
A30: ITSS Cisco LoB | B30: TFG | C30: FSI & Retail | D30: OPP147999/02 | E30: 1343561.1 | F30: 67178.056 | G30: 67178.056 | H30: 0.05 | I30: Upside | J30: 46204 | K30: FY 27 Q2 | L30: No | M30: Upside Deal | N30: Low | P30: Olden Pieterse | Q30: Wimpie Pieterse | R30: Product | S30: Ndabeni Wireless - Submitted Quote
A31: ITSS Cisco LoB | B31: Shoprite | C31: FSI & Retail | D31: OPP141634 | E31: 1161340 | F31: 1161340 | G31: 81293.799 | H31: 0.07 | I31: Upside | J31: 46235 | K31: FY 27 Q2 | L31: No | M31: Upside Deal | N31: Medium | P31: Olden Pieterse | Q31: Wandile Dlamini | R31: Product | S31: EDD 64 days from order - OPP145772 Concentrix Arch Bldg Durban
A32: ITSS Cisco LoB | B32: The Spar Group Ltd | C32: FSI & Retail | D32: OPP147984 | E32: 635950 | F32: 635950 | G32: 76314 | H32: 0.12 | I32: Commit | J32: 46174 | K32: FY 27 Q1 | L32: No | M32: Backlog Deal | N32: High | O32: Checked | P32: Olden Pieterse | Q32: Wimpie Pieterse | R32: Product | S32: 100 x MX67 details to follow - Received order
A33: ITSS Cisco LoB | B33: Pioneer Foods (Pty) Ltd | C33: FSI & Retail | D33: OPP136578/03 | E33: 626376 | F33: 626376 | G33: 62637.6 | H33: 0.1 | I33: Commit | J33: 46388 | K33: FY 27 Q4 | L33: No | M33: Backlog Deal | N33: High | P33: Olden Pieterse | Q33: Wimpie Pieterse | R33: Product | S33: Expected Delivery Date end of May - Worcester Bakery - order received
A34: ITSS Cisco LoB | B34: The Spar Group Ltd | C34: FSI & Retail | D34: OPP146350 | E34: 617291.28 | F34: 617291.28 | G34: 74074.954 | H34: 0.12 | I34: Commit | J34: 46143 | K34: FY 27 Q1 | L34: Yes | M34: Backlog Deal | N34: High | P34: Olden Pieterse | Q34: Wimpie Pieterse | R34: Product | S34: Spar Co cameras
A35: ITSS Cisco LoB | B35: Sanlam Life Insurance Limited | C35: FSI & Retail | D35: OPP146359 | E35: 594982.92 | F35: 594982.92 | G35: 59498.292 | H35: 0.1 | I35: Commit | J35: 46143 | K35: FY 27 Q1 | L35: No | M35: Backlog Deal | N35: High | P35: Sean Royds | Q35: Wimpie Pieterse | R35: Product | S35: EDD 4 May
A36: ITSS Cisco LoB | B36: Pioneer Foods (Pty) Ltd | C36: FSI & Retail | D36: OPP136577/03 | E36: 934980 | F36: 93498 | G36: 93498 | H36: 0.1 | I36: Commit | J36: 46388 | K36: FY 27 Q4 | L36: No | M36: Backlog Deal | N36: High | P36: Olden Pieterse | Q36: Wimpie Pieterse | R36: Product | S36: EDD May - Ceres Beverages - order received
A37: ITSS Cisco LoB | B37: Bigen Africa Group Holdings | C37: Corporate | D37: OPP132134 | E37: 1945541.9 | F37: 1945541.9 | G37: 194554.19 | H37: 0.1 | I37: Commit | J37: 46174 | K37: FY 27 Q1 | L37: No | M37: Backlog Deal | N37: High | O37: Checked | P37: Wandile Dlamini | Q37: Wimpie Pieterse | R37: Product | S37: Delivered, waiting for invoice / Invoiced 90990473 (2026/03/24) but Installation by Field Services Outstanding
A38: ITSS Cisco LoB | B38: Nedbank Limited | C38: FSI & Retail | D38: OPP147047 | E38: 907344 | F38: 54440.64 | G38: 54440.64 | H38: 0.06 | I38: Upside | J38: 46235 | K38: FY 27 Q2 | L38: No | M38: Upside Deal | N38: Medium | O38: Checked | P38: Sean Royds | Q38: Wimpie Pieterse | R38: Product | S38: Upgrade Backbone connectivity to DWDM system and expansion to ADC DC for Azure Redundnacy - CY Q4 2026
A39: ITSS Cisco LoB | B39: Sanlam Life Insurance Limited | C39: FSI & Retail | D39: OPP146568 | E39: 404189.72 | F39: 404189.72 | G39: 40418.972 | H39: 0.1 | I39: Upside | J39: 46204 | K39: FY 27 Q2 | L39: No | M39: Upside Deal | N39: Medium | O39: Checked | P39: Sean Royds | Q39: Wimpie Pieterse | R39: Product | S39: EDD 63 days from order placement - RM 2027 EOL Replacements
A40: ITSS Cisco LoB | B40: Tiger Consumer Brands Limited | C40: FSI & Retail | D40: OPP146881 | E40: 365524 | F40: 36552.4 | G40: 36552.4 | H40: 0.1 | I40: Upside | J40: 46204 | K40: FY 27 Q2 | L40: No | M40: Upside Deal | N40: Medium | P40: Nowell Duze | Q40: Wimpie Pieterse | R40: Software / Licence | S40: Quote refreshed on the 17th of May. Tiger brands has to renew this month
A41: ITSS Cisco LoB | B41: Sanlam Life Insurance Limited | C41: FSI & Retail | D41: OPP146570 | E41: 313403.48 | F41: 313403.48 | G41: 31340.348 | H41: 0.1 | I41: Upside | J41: 46204 | K41: FY 27 Q2 | L41: No | M41: Upside Deal | N41: Medium | O41: Checked | P41: Sean Royds | Q41: Wimpie Pieterse | R41: Product | S41: EDD 70 days from order placement - STM 2027 EOL Replacements
A42: ITSS Cisco LoB | B42: Openserve (Pty) Ltd | C42: Mining Indust&Health | D42: OPP145588 | E42: 13312345 | F42: 665617.25 | G42: 665617.25 | H42: 0.05 | I42: Upside | J42: 46539 | L42: No | M42: Upside Deal | N42: High | O42: checked | P42: Johan Taljaard | Q42: Wimpie Pieterse | R42: OEM Service | S42: Opernserve Sweep Year 2 of 3, June 2027
A43: ITSS Cisco LoB | B43: Openserve (Pty) Ltd | C43: Mining Indust&Health | D43: OPP145588 | E43: 13312345 | F43: 665617.25 | G43: 665617.25 | H43: 0.05 | I43: Upside | J43: 46539 | L43: No | M43: Upside Deal | N43: High | O43: checked | P43: Johan Taljaard | Q43: Wimpie Pieterse | R43: OEM Service | S43: Opernserve Sweep Year 3 of 3, June 2028
A44: ITSS Cisco LoB | B44: Sanlam Life Insurance Limited | C44: FSI & Retail | D44: OPP146569 | E44: 226989.87 | F44: 226989.87 | G44: 22698.987 | H44: 0.1 | I44: Upside | J44: 46204 | K44: FY 27 Q2 | L44: No | M44: Upside Deal | N44: Medium | O44: Checked | P44: Sean Royds | Q44: Wimpie Pieterse | R44: Product | S44: EDD 70 days from order placement - SIM 2027 EOL Replacements
A45: ITSS Cisco LoB | B45: Aspen SA Operations (Pty) Ltd | C45: Corporate | D45: OPP144676 | E45: 965955.74 | F45: 965955.74 | G45: 96595.574 | H45: 0.1 | I45: Commit | J45: 46143 | K45: FY 27 Q1 | L45: No | M45: Backlog Deal | N45: High | O45: checked | P45: Roan van Nieuwenhuizen | Q45: Wimpie Pieterse | R45: Product | S45: EDD - 15 June 2026
A46: ITSS Cisco LoB | B46: Concentrix CVG South Africa(Pty) Ltd | C46: Corporate | D46: OPP142082 | E46: 917225.58 | F46: 917225.58 | G46: 55033.535 | H46: 0.06 | I46: Commit | J46: 46174 | K46: FY 27 Q1 | L46: No | M46: Backlog Deal | N46: High | O46: Checked | P46: Olden Pieterse | Q46: Wimpie Pieterse | R46: Product | S46: Invoicing moved out to June because of 28 May SW start date - CPT SD WAN Routers
A47: ITSS Cisco LoB | B47: CEOS Technologies | C47: Corporate | D47: OPP147144 | E47: 168111 | F47: 168111 | G47: 16811.1 | H47: 0.1 | I47: Upside | J47: 46174 | K47: FY 27 Q1 | L47: No | M47: Upside Deal | N47: High | O47: checked | P47: Johan Taljaard | Q47: Wimpie Pieterse | R47: Product | S47: Meraki mx85's
A48: ITSS Cisco LoB | B48: Sanlam | C48: FSI & Retail | D48: OPP146954 | E48: 3127270.3 | F48: 312727.03 | G48: 312727.03 | H48: 0.1 | I48: Upside | J48: 46266 | K48: FY 27 Q2 | L48: No | M48: Upside Deal | N48: High | O48: Checked | P48: Sean Royds | Q48: Wimpie Pieterse | R48: Product | S48: Sanlam reviewing to potentially bundle deals together
A49: ITSS Cisco LoB | B49: RCL Chicken - Head Office | C49: Corporate | D49: OPP145709 | E49: 578400.08 | F49: 57840.01 | G49: 57840.008 | H49: 0.1 | I49: Commit | J49: 46143 | K49: FY 27 Q1 | L49: Yes | M49: Backlog Deal | N49: High | O49: Checked | P49: Hein Botha | Q49: Wimpie Pieterse | R49: Software / Licence | S49: Wimpie Rectified Discount Issue
A50: ITSS Cisco LoB | B50: BASF Catalysts SouthAfrica (Pty) Ltd | C50: Corporate | D50: OPP147662 | E50: 226470 | F50: 226470 | G50: 22647 | H50: 0.1 | I50: Commit | J50: 46174 | K50: FY 27 Q1 | L50: No | M50: Backlog Deal | N50: High | P50: Roan van Nieuwenhuizen | Q50: Wimpie Pieterse | R50: Product | S50: C8235-G2 SD-WAN Routers
A51: ITSS Cisco LoB | B51: Fresenius Kabi South Africa (Pty) L | C51: Corporate | D51: OPP145651 | E51: 180432.75 | F51: 18043.275 | G51: 18043.275 | H51: 0.1 | I51: Commit | J51: 46143 | K51: FY 27 Q1 | L51: Yes | M51: Backlog Deal | N51: High | O51: Checked | P51: Lawrence Lethuba | Q51: Wimpie Pieterse | R51: Product | S51: Invoiced 4 May - Swtiches
A52: ITSS Cisco LoB | B52: Pioneer Foods (Pty) Ltd | C52: FSI & Retail | D52: OPP136533/03 | E52: 425312 | F52: 425312 | G52: 42531.2 | H52: 0.1 | I52: Commit | J52: 46388 | K52: FY 27 Q4 | L52: No | M52: Backlog Deal | N52: High | P52: Olden Pieterse | Q52: Wimpie Pieterse | R52: Product | S52: EDD June - Cereals Epping - order received
A53: ITSS Cisco LoB | B53: Stanlib Assets Management Limited | C53: FSI & Retail | D53: OPP123194 | E53: 624265 | F53: 62426.5 | G53: 62426.5 | H53: 0.1 | I53: Commit | J53: 46204 | K53: FY 27 Q2 | L53: No | M53: Backlog Deal | N53: High | O53: Checked | P53: Paul van Rooyen | Q53: Wimpie Pieterse | R53: Software / Licence | S53: Stanlib APP-D year 2/3
A54: ITSS Cisco LoB | B54: Pioneer Foods (Pty) Ltd | C54: FSI & Retail | D54: OPP144496/01 | E54: 503411 | F54: 50341.1 | G54: 50341.1 | H54: 0.1 | I54: Commit | J54: 46388 | K54: FY 27 Q4 | L54: No | M54: Backlog Deal | N54: High | P54: Olden Pieterse | Q54: Wimpie Pieterse | R54: Product | S54: Ship from Cisco End of May - Delivered to BCX 3rd week in June - Isando Router & Switches - order received
A55: ITSS Cisco LoB | B55: Pioneer Foods (Pty) Ltd | C55: FSI & Retail | D55: OPP147653 | E55: 488137.02 | F55: 488137.02 | G55: 48813.702 | H55: 0.1 | I55: Commit | J55: 46388 | K55: FY 27 Q4 | L55: No | M55: Backlog Deal | N55: High | P55: Olden Pieterse | Q55: Wimpie Pieterse | R55: Product | S55: Ship date from Cisco 17Aug
A56: ITSS Cisco LoB | B56: Pioneer Foods (Pty) Ltd | C56: FSI & Retail | D56: OPP147659 | E56: 351564.51 | F56: 351564.51 | G56: 35156.451 | H56: 0.1 | I56: Commit | J56: 46388 | K56: FY 27 Q4 | L56: No | M56: Backlog Deal | N56: High | P56: Olden Pieterse | Q56: Wimpie Pieterse | R56: Product | S56: Ship date from Cisco 13Aug
A57: ITSS Cisco LoB | B57: Telkom Consumer | C57: Mining Indust&Health | D57: OPP142649/02 | E57: 13140597 | F57: 13140597 | G57: 1182653.7 | H57: 0.09 | I57: Upside | J57: 46327 | K57: FY 27 Q3 | L57: No | M57: Upside Deal | N57: High | O57: checked | P57: Johan Taljaard | Q57: Wimpie Pieterse | R57: Product | S57: EDD 42 days after order placement - EoL Switches
A58: ITSS Cisco LoB | B58: Sanlam Life Insurance Limited | C58: FSI & Retail | D58: OPP146430 | E58: 1086871.8 | F58: 1086871.8 | G58: 108687.18 | H58: 0.06 | I58: Upside | J58: 46204 | K58: FY 27 Q2 | L58: No | M58: Upside Deal | N58: High | O58: Checked | P58: Sean Royds | Q58: Wimpie Pieterse | R58: Product | S58: Cancelled to be ordered as complete SIP solution in next two weeks.
A59: ITSS Cisco LoB | B59: Pioneer Foods (Pty) Ltd | C59: FSI & Retail | D59: OPP147899 | E59: 124832.9 | F59: 12483.29 | G59: 12483.29 | H59: 0.1 | I59: Upside | J59: 46204 | K59: FY 27 Q2 | L59: No | M59: Upside Deal | N59: Medium | P59: Olden Pieterse | Q59: Wimpie Pieterse | R59: Product | S59: Isando Switches : Details to follow
A60: ITSS Cisco LoB | B60: South African Revenue Services | C60: Public | D60: OPP145398 | E60: 2.4910934e+08 | F60: 2.4910934e+08 | G60: 19928747 | H60: 0.08 | I60: Upside | J60: 46447 | K60: FY 27 Q4 | L60: No | M60: Upside Deal | N60: Low | P60: David Ramorola | Q60: Wimpie Pieterse | R60: Product | S60: RFP - TowerD Secure Access, 1000Eyes, Meraki switches(5years)
A61: ITSS Cisco LoB | B61: South African Social Agency (SASSA) | C61: Public | D61: OPP146677 | E61: 1.235666e+08 | F61: 1.235666e+08 | G61: 6178330.2 | H61: 0.05 | I61: Upside | J61: 46447 | K61: FY 27 Q4 | L61: No | M61: Upside Deal | N61: Low | P61: David Ramorola | Q61: Wimpie Pieterse | R61: Product | S61: RFQ - Meraki SD-Wan + Security (Switches and Sec-SUITE)
A62: ITSS Cisco LoB | B62: Telkom ISP | C62: Mining Indust&Health | D62: OPP147364 | E62: 28723558 | F62: 2872355.8 | G62: 2872355.8 | H62: 0.1 | I62: Upside | J62: 46327 | K62: FY 27 Q3 | L62: No | M62: Upside Deal | N62: Medium | O62: checked | P62: Johan Taljaard | Q62: Wimpie Pieterse | R62: Software / Licence | S62: DDOS
A63: ITSS Cisco LoB | B63: Openserve (Pty) Ltd | C63: Mining Indust&Health | D63: OPP145768 | E63: 21938053 | F63: 1096902.6 | G63: 1096902.6 | H63: 0.05 | I63: Upside | J63: 46327 | K63: FY 27 Q3 | L63: No | M63: Upside Deal | N63: Medium | O63: checked | P63: Johan Taljaard | Q63: Wimpie Pieterse | R63: Product | S63: FW budget prep 10 x FW's + secure workload
A64: ITSS Cisco LoB | B64: The Standard Bank of South Africa | C64: FSI & Retail | D64: OPP13777 | E64: 17211644 | F64: 1721164.4 | G64: 1721164.4 | H64: 0.1 | I64: Commit | J64: 46478 | L64: No | M64: Backlog Deal | N64: High | O64: Checked | P64: Paul van Rooyen | Q64: Wimpie Pieterse | R64: Software / Licence | S64: APP-D EA Renewal
A65: ITSS Cisco LoB | B65: Openserve (Pty) Ltd | C65: Mining Indust&Health | D65: OPP141512/01 | E65: 14895000 | F65: 14895000 | G65: 1489500 | H65: 0.1 | I65: Upside | J65: 46327 | K65: FY 27 Q3 | L65: No | M65: Upside Deal | N65: Medium | O65: checked | P65: Johan Taljaard | Q65: Wimpie Pieterse | R65: Product | S65: International POPS - Telkom wants eq for evaluation before project go ahead
A66: ITSS Cisco LoB | B66: SANBS | C66: Public | D66: OPP146783 | E66: 14433451 | F66: 721672.55 | G66: 721672.55 | H66: 0.05 | I66: Upside | J66: 46296 | K66: FY 27 Q3 | L66: No | M66: Upside Deal | N66: Low | O66: Checked | P66: Wandile Dlamini | Q66: Wimpie Pieterse | R66: OEM Service | S66: Current support expires at the end of Sep-2026
A67: ITSS Cisco LoB | B67: Durban ICC | C67: Public | D67: OPP145736 | E67: 7845333 | F67: 7845333 | G67: 392266.65 | H67: 0.05 | I67: Upside | J67: 46266 | K67: FY 27 Q2 | L67: No | M67: Upside Deal | N67: Medium | O67: Checked | P67: Wandile Dlamini | Q67: Wimpie Pieterse | R67: Product | S67: EDD 100 days - Wireless refresh
A68: ITSS Cisco LoB | B68: Telkom SA SOC Limited | C68: Mining Indust&Health | D68: OPP122332/04 | E68: 11391262 | F68: 569563.1 | G68: 569563.1 | H68: 0.05 | I68: Commit | J68: 46204 | K68: FY 27 Q2 | L68: No | M68: Backlog Deal | N68: High | O68: checked | P68: johan Taljaard | Q68: Wimpie Pieterse | R68: OEM Service | S68: APP-D EA Year 2/3
A69: ITSS Cisco LoB | B69: Telkom Consumer | C69: Mining Indust&Health | D69: OPP142649/01 | E69: 10827243 | F69: 10827243 | G69: 974451.85 | H69: 0.09 | I69: Upside | J69: 46327 | K69: FY 27 Q3 | L69: No | M69: Upside Deal | N69: High | O69: checked | P69: Johan Taljaard | Q69: Wimpie Pieterse | R69: Product | S69: EDD 58 days after order placement - Line Cards
A70: ITSS Cisco LoB | B70: Woolworths (Pty) Limited | C70: FSI & Retail | D70: OPP128359 | E70: 13294957 | F70: 13294957 | G70: 1329495.7 | H70: 0.1 | I70: Commit | J70: 46266 | K70: FY 27 Q2 | L70: No | M70: Committed Pipe Deal | N70: High | P70: Olden Pieterse | Q70: Wimpie Pieterse | R70: Product | S70: Operate UC in Contract discussion with customer
A71: ITSS Cisco LoB | B71: Telkom SA SOC Limited | C71: Mining Indust&Health | D71: OPP135119 | E71: 13162789 | F71: 13162789 | G71: 1316278.9 | H71: 0.1 | I71: Upside | J71: 46327 | K71: FY 27 Q3 | L71: No | M71: Upside Deal | N71: Medium | O71: checked | P71: Johan Taljaard | Q71: Wimpie Pieterse | R71: Product | S71: Telkom Nutanix expansion
A72: ITSS Cisco LoB | B72: Openserve (Pty) Ltd | C72: Mining Indust&Health | D72: OPP131296 | E72: 2708682 | F72: 270868.2 | G72: 270868.2 | H72: 0.1 | I72: Commit | J72: 46174 | K72: FY 27 Q1 | L72: No | M72: Backlog Deal | N72: High | O72: checked | P72: Johan Taljaard | Q72: Wimpie Pieterse | R72: OEM Service | S72: Cisco Advanced Services
A73: ITSS Cisco LoB | B73: Air Traffic and Navigation ServicesCompany Limited | C73: Public | D73: OPP123907 | E73: 12000000 | F73: 12000000 | G73: 375152 | H73: 0.1 | I73: Upside | J73: 46447 | K73: FY 27 Q4 | L73: No | M73: Upside Deal | N73: Low | O73: Checked | P73: Wandile Dlamini | Q73: Wimpie Pieterse | R73: Product | S73: Ongoing Tender - Waiting for award for more than a year
A74: ITSS Cisco LoB | B74: Western Cape Government Health | C74: Public | D74: OPP140607 | E74: 10854175 | F74: 10854175 | G74: 542708.75 | H74: 0.05 | I74: Upside | J74: 46296 | K74: FY 27 Q3 | L74: No | M74: Upside Deal | N74: Low | O74: Checked | P74: Wandile Dlamini | Q74: Wimpie Pieterse | R74: Product | S74: EDD 45 days - LAN refresh - customer asked for bid evaluation extension until 01-Aug-2026
A75: ITSS Cisco LoB | B75: Telkom SA SOC Limited | C75: Mining Indust&Health | D75: OPP125388/06 | E75: 2227444.7 | F75: 2227141.6 | G75: 222714.16 | H75: 0.1 | I75: Commit | J75: 46174 | K75: FY 27 Q1 | L75: No | M75: Backlog Deal | N75: High | O75: checked | P75: Johan Taljaard | Q75: Wimpie Pieterse | R75: Product | S75: EDD Late May - Telkom TCnet Campus Refresh, business case is approved, contract still pending
A76: ITSS Cisco LoB | B76: Volkswagen Group Africa (Pty) Ltd | C76: Corporate | D76: OPP148038 | E76: 7461453 | F76: 7461453 | G76: 746145.3 | H76: 0.1 | I76: Upside | J76: 46235 | K76: FY 27 Q2 | L76: No | M76: Upside Deal | N76: Low | P76: Roan van Nieuwenhuizen | Q76: Wimpie Pieterse | R76: Product | S76: Respond to RFQ for Kariga Firewals
A77: ITSS Cisco LoB | B77: Pep A Division Of Pepkor Trading (PTd | C77: Corporate | D77: OPP146179 | E77: 8123456 | F77: 974814.72 | G77: 974814.72 | H77: 0.12 | I77: Upside | J77: 46327 | K77: FY 27 Q3 | L77: No | M77: Upside Deal | N77: High | O77: checked | P77: Roan van Nieuwenhuizen | Q77: Wimpie Pieterse | R77: Software / Licence | S77: Working on a 3 and 5 year EA Renewal. Customer will release an RFQ, EA expiring in Nov 2026
A78: ITSS Cisco LoB | B78: Electoral Commission of SouthAfrica Iec | C78: Public | D78: OPP147418 | E78: 7405205 | F78: 7405205 | G78: 740520.5 | H78: 0.1 | I78: Upside | J78: 46266 | K78: FY 27 Q2 | L78: No | M78: Upside Deal | N78: Low | P78: Roan van Nieuwenhuizen | Q78: Wimpie Pieterse | R78: Product | S78: IEC Wireless Solution
A79: ITSS Cisco LoB | B79: Volkswagen Group Africa (Pty) Ltd | C79: Corporate | D79: OPP146486 | E79: 5751314 | F79: 5751314 | G79: 575131.4 | H79: 0.1 | I79: Upside | J79: 46235 | K79: FY 27 Q2 | L79: No | M79: Upside Deal | N79: Low | P79: Roan van Nieuwenhuizen | Q79: Wimpie Pieterse | R79: Product | S79: Provide Security EA Proposal
A80: ITSS Cisco LoB | B80: Pep A Division Of Pepkor Trading (PTd | C80: Corporate | D80: OPP141566 | E80: 6991803.2 | F80: 6991803.2 | G80: 489426.23 | H80: 0.07 | I80: Upside | J80: 46419 | K80: FY 27 Q4 | L80: No | M80: Upside Deal | N80: Medium | O80: checked | P80: Paul van Rooyen | Q80: Wimpie Pieterse | R80: Product | S80: Capfin Catalyst refresh
A81: ITSS Cisco LoB | B81: Sasol South Africa Limited | C81: Mining Indust&Health | D81: OPP146361 | E81: 4057210.5 | F81: 4057210.5 | G81: 405721.05 | H81: 0.1 | I81: Commit | J81: 46204 | K81: FY 27 Q2 | L81: No | M81: Backlog Deal | N81: High | P81: Nowell Duze | Q81: Wimpie Pieterse | R81: Product | S81: Thubelisha - Switches & SFP's
A82: ITSS Cisco LoB | B82: Capitec Bank Limited | C82: FSI & Retail | D82: OPP089485 | E82: 5699203 | F82: 159577.68 | G82: 159577.68 | H82: 0.028 | I82: Commit | J82: 46327 | K82: FY 27 Q3 | L82: No | M82: Backlog Deal | N82: High | O82: checked | P82: Paul van Rooyen | Q82: Wimpie Pieterse | R82: Software / Licence | S82: SDWAN EA Annual payment
A83: ITSS Cisco LoB | B83: AVI Financial Services (Pty) Ltd | C83: Corporate | D83: OPP125425/14 | E83: 3341660.3 | F83: 3341660.3 | G83: 167083.02 | H83: 0.05 | I83: Upside | J83: 46266 | K83: FY 27 Q2 | L83: No | M83: Upside Deal | N83: Medium | O83: checked | P83: Lawrence Lethuba | Q83: Wimpie Pieterse | R83: Product | S83: EDD 42 days after order placement - Network refresh for Isando DC
A84: ITSS Cisco LoB | B84: Sanlam Life Insurance Limited | C84: FSI & Retail | D84: OPP145901 | E84: 4249038.3 | F84: 4249038.3 | G84: 424903.83 | H84: 0.1 | I84: Commit | J84: 46327 | K84: FY 27 Q3 | L84: No | M84: Backlog Deal | N84: High | P84: Sean Royds | Q84: Wimpie Pieterse | R84: Product | S84: EDD 3 June 2026
A85: ITSS Cisco LoB | B85: AVI Financial Services (Pty) Ltd | C85: Corporate | D85: OPP125425/13 | E85: 4181579.7 | F85: 209078.99 | G85: 209078.99 | H85: 0.05 | I85: Upside | J85: 46296 | K85: FY 27 Q3 | L85: No | M85: Upside Deal | N85: High | O85: checked | P85: Lawrence Lethuba | Q85: Wimpie Pieterse | R85: Software / Licence | S85: OPP125425_13 - AVI - EA - 60 Months & 84 Months_V5
A86: ITSS Cisco LoB | B86: Sasol South Africa Limited | C86: Mining Indust&Health | D86: OPP147303 | E86: 4120766.5 | F86: 4120766.5 | G86: 412076.65 | H86: 0.1 | I86: Commit | J86: 46174 | K86: FY 27 Q1 | L86: No | M86: Backlog Deal | N86: High | P86: Nowell Duze | Q86: Wimpie Pieterse | R86: Product | S86: Project missing Persons( Industrial switches) shipdate 5th August
A87: ITSS Cisco LoB | B87: Cape Peninsula University of Techno | C87: Public | D87: OPP146451 | E87: 2750816.6 | F87: 2304216.6 | G87: 275081.66 | H87: 0.1 | I87: Commit | J87: 46235 | K87: FY 27 Q2 | L87: No | M87: Backlog Deal | N87: High | P87: Olden Pieterse | Q87: Wimpie Pieterse | R87: Product | S87: EDD 16 July -
A88: ITSS Cisco LoB | B88: Ethekwini Municipality | C88: Public | D88: OPP146897 | E88: 2855832 | F88: 2855832 | G88: 142791.6 | H88: 0.05 | I88: Upside | J88: 46235 | K88: FY 27 Q2 | L88: No | M88: Upside Deal | N88: Low | O88: Checked | P88: Wandile Dlamini | Q88: Wimpie Pieterse | R88: Product | S88: EDD 105 - Network refresh - Wireless and MetroE routers
A89: ITSS Cisco LoB | B89: AVI Financial Services (Pty) Ltd | C89: Corporate | D89: OPP132983 | E89: 3498223.4 | F89: 3498223.4 | G89: 174911.17 | H89: 0.05 | I89: Upside | J89: 46266 | K89: FY 27 Q2 | L89: No | M89: Upside Deal | N89: High | O89: checked | P89: Lawrence Lethuba | Q89: Wimpie Pieterse | R89: Product | S89: EDD 58 days after order placement - EoL Replacements Bryanston HQ - Awaiting customer decision - awaiting Andre
A90: ITSS Cisco LoB | B90: Sanlam | C90: FSI & Retail | D90: OPP146118 | E90: 94804.79 | F90: 9480.479 | G90: 9480.479 | H90: 0.1 | I90: Upside | J90: 46266 | K90: FY 27 Q2 | L90: No | M90: Upside Deal | N90: Medium | P90: Sean Royds | Q90: Wimpie Pieterse | R90: Product | S90: Sanlam reviewing to potentially bundle deals together
A91: ITSS Cisco LoB | B91: FNZ Software Solutions | C91: Corporate | D91: OPP146221 | E91: 3158297 | F91: 3158297 | G91: 315829.7 | H91: 0.1 | I91: Upside | J91: 46296 | K91: FY 27 Q3 | L91: No | M91: Upside Deal | N91: Medium | O91: Checked | P91: Wandile Dlamini | Q91: Wimpie Pieterse | R91: Product | S91: EDD 135 days for the SFPs
A92: ITSS Cisco LoB | B92: AVI Financial Services (Pty) Ltd | C92: Corporate | D92: OPP125425/08 | E92: 3066160 | F92: 3066160 | G92: 153308 | H92: 0.05 | I92: Upside | J92: 46266 | K92: FY 27 Q2 | L92: No | M92: Upside Deal | N92: High | O92: checked | P92: Lawrence Lethuba | Q92: Wimpie Pieterse | R92: Product | S92: EDD 42 days after order placement - EoL Replacements Retail stores
A93: ITSS Cisco LoB | B93: Mossel Bay Municipality | C93: Public | D93: OPP145648 | E93: 2725320 | F93: 2725320 | G93: 272532 | H93: 0.1 | I93: Upside | J93: 46266 | K93: FY 27 Q2 | L93: No | M93: Upside Deal | N93: Low | O93: Checked | P93: Wandile Dlamini | Q93: Wimpie Pieterse | R93: Product | S93: EDD 57 days - IP phones and Voice Gateway - Includes SIP services
A94: ITSS Cisco LoB | B94: AVI Financial Services (Pty) Ltd | C94: Corporate | D94: OPP137317 | E94: 2701274.2 | F94: 2701274.2 | G94: 135063.71 | H94: 0.05 | I94: Upside | J94: 46266 | K94: FY 27 Q2 | L94: No | M94: Upside Deal | N94: High | O94: checked | P94: Lawrence Lethuba | Q94: Wimpie Pieterse | R94: Product | S94: EDD 44 days after order placement - EoL Replacements Isando Biscuits
A95: ITSS Cisco LoB | B95: Old Mutual Insure Limited | C95: FSI & Retail | D95: OPP144877 | E95: 3000000 | F95: 300000 | G95: 300000 | H95: 0.1 | I95: Upside | J95: 46296 | K95: FY 27 Q3 | L95: No | M95: Upside Deal | N95: Medium | O95: Checked | P95: Sean Royds | Q95: Wimpie Pieterse | R95: Product | S95: DC and Wireless Reresh towards latter part of CY 2026 or early CY 2027
A96: ITSS Cisco LoB | B96: Nedbank Limited | C96: FSI & Retail | D96: OPP146356 | E96: 2929292.9 | F96: 241318.76 | G96: 241318.76 | H96: 0.056 | I96: Upside | J96: 46419 | K96: FY 27 Q4 | L96: No | M96: Upside Deal | N96: High | O96: Checked | P96: Sean Royds | Q96: Wimpie Pieterse | R96: Software / Licence | S96: Licensing Renewal, want to include this in the current EA as addition Tier, currnet licenses expire end May 2026
A97: ITSS Cisco LoB | B97: Woolworths (Pty) Limited | C97: FSI & Retail | D97: OPP147673 | E97: 68258.96 | F97: 6825.896 | G97: 6825.896 | H97: 0.1 | I97: Upside | J97: 46204 | K97: FY 27 Q2 | L97: No | M97: Upside Deal | N97: Medium | P97: Olden Pieterse | Q97: Wimpie Pieterse | R97: Product | S97: Subitted Pricing
A98: ITSS Cisco LoB | B98: Nelson Mandela Children's Hospital | C98: Public | D98: OPP148147 | E98: 2703682.7 | F98: 2703682.7 | G98: 324441.92 | H98: 0.12 | I98: Upside | J98: 46266 | K98: FY 27 Q2 | L98: No | M98: Upside Deal | N98: Low | O98: Checked | P98: Wandile Dlamini | Q98: Wimpie Pieterse | R98: Product | S98: EDD 120 days for the WLC - RFQ Wireless refresh
A99: ITSS Cisco LoB | B99: Blake And Associates | C99: Corporate | D99: OPP146206 | E99: 2057983 | F99: 2057983 | G99: 205798.3 | H99: 0.1 | I99: Commit | J99: 46235 | K99: FY 27 Q2 | L99: No | M99: Backlog Deal | N99: High | O99: checked | P99: Johan Taljaard | Q99: Wimpie Pieterse | R99: Product | S99: Distribution, access switches and AP's
A100: ITSS Cisco LoB | B100: Volkswagen Group Africa (Pty) Ltd | C100: Corporate | D100: OPP147266 | E100: 1355862 | F100: 1355862 | G100: 135586.2 | H100: 0.1 | I100: Upside | J100: 46235 | K100: FY 27 Q2 | L100: No | M100: Upside Deal | N100: Low | P100: Roan van Nieuwenhuizen | Q100: Wimpie Pieterse | R100: Product | S100: Respond to RFQ for Regional Firewalls
...
